Workbook
Name Bahraini: List!$F$6:$I$6
Name Bespoke: List!$F$5:$R$5
Name ContractForms: List!$E$2:$E$6
Name ECC: List!$F$3:$K$3
Name Fidic: List!$F$2:$O$2
Name ICE: List!$F$4:$K$4
Name YesNo: List!$C$15:$C$16

Sheet TenderInfo
A1: Tender Data Form
A3: Basic Info
A4: Tender No. | B4: 1743-01 | C4: (Ex 1500-01) | E4: This cell should match with the tendernumber in the database
A5: Revision No. | B5: 0 | C5: (Ex 1) | E5: This cell should match with the revisionnumber in the database
A7: Other info to be filled in immediately in the database!

Sheet DataForm
A1: Tender Data Form
A3: Title | C3: BS-BAHRAIN-Expansion of Storage Yard Area
A4: Tender No. | C4: 1743-01
A5: Tender Currency | C5: AED
A6: Currency Rate
A8: [AED] | C8: Equipment | E8: Fuel | F8: Materials | M8: Personnel | O8: Misc | P8: Subcontractor | Q8: Total Cost | R8: Mark-ups | U8: Total (excl. Tax) | V8: Tax | X8: Total (incl. Tax) | Z8: Quantities | AA8: Unit | AB8: Remarks
B9: Item | C9: Internal | D9: External | F9: Pipeline | G9: Teeth | H9: Steel | I9: Rock | J9: Concrete | K9: Other | L9: Total Materials | M9: Labour | N9: Staff | R9: Risk [%] | S9: Overhead [%] | T9: Profit [%] | V9: Direct | W9: Indirect
A10: A | B10: Mob/Demob | C10: =C11+C12 -> 913433.1 | D10: =D11+D12 -> 556550.62 | E10: =E11+E12 -> 1361099 | F10: =F11+F12 -> 76038.552 | G10: =G11+G12 -> 0 | H10: =H11+H12 -> 0 | I10: =I11+I12 -> 0 | J10: =J11+J12 -> 0 | ... P10: =P11+P12 -> 549999.82 | Q10: =C10+D10+E10+F10+G10+H10+I10+J10+K10+M10+N10+O10+P10 -> 7115827.2 | U10: =U11+U12 -> 8938173.2 | X10: =X11+X12 -> 8938173.2
A11: A.1 | B11: Mobilization | C11: 565050.9 | D11: 291308.83 | E11: 831312.11 | F11: 45623.131 | G11: 0 | H11: 0 | I11: 0 | J11: 0 | K11: 113678.05 | M11: 209495.73 | N11: 457963.25 | O11: 2079666.6 | P11: =240946.089662165+125000 -> 365946.09 | Q11: =C11+D11+E11+F11+G11+H11+I11+J11+K11+M11+N11+O11+P11 -> 4960044.7 | R11: 0.03 | S11: 0.08 | T11: 0.1 | U11: =((1+R11)/(1-S11-T11))*Q11 -> 6230300.1 | V11: 0 | X11: =U11+V11+W11 -> 6230300.1
A12: A.2 | B12: Demobilization | C12: 348382.2 | D12: 265241.78 | E12: 529786.91 | F12: 30415.421 | G12: 0 | H12: 0 | I12: 0 | J12: 0 | K12: 75785.365 | M12: 127907.02 | N12: 261887.55 | O12: 332322.54 | P12: 184053.73 | Q12: =C12+D12+E12+F12+G12+H12+I12+J12+K12+M12+N12+O12+P12 -> 2155782.5 | R12: 0.03 | S12: 0.08 | T12: 0.1 | U12: =((1+R12)/(1-S12-T12))*Q12 -> 2707873.2 | V12: 0 | X12: =U12+V12+W12 -> 2707873.2
A14: B | B14: Preliminaries | C14: =C15+C19 -> 42558.48 | D14: =D15+D19 -> 1951164 | E14: =E15+E19 -> 479155.21 | F14: =F15+F19 -> 0 | G14: =G15+G19 -> 0 | H14: =H15+H19 -> 0 | I14: =I15+I19 -> 0 | J14: =J15+J19 -> 800 | ... P14: =P15+P19 -> 399517 | Q14: =C14+D14+E14+F14+G14+H14+I14+J14+K14+M14+N14+O14+P14 -> 15744458 | U14: =U15+U19 -> 19776575 | X14: =X15+X19 -> 19776575
A15: B.1 | B15: Fixed Prelimanary costs | C15: =C16+C17+C18 -> 42558.48 | D15: =D16+D17+D18 -> 363816 | E15: =E16+E17+E18 -> 86760.966 | F15: =F16+F17+F18 -> 0 | G15: =G16+G17+G18 -> 0 | H15: =H16+H17+H18 -> 0 | I15: =I16+I17+I18 -> 0 | J15: =J16+J17+J18 -> 800 | ... P15: =P16+P17+P18 -> 121000 | Q15: =C15+D15+E15+F15+G15+H15+I15+J15+K15+M15+N15+O15+P15 -> 4634349 | U15: =U16+U17+U18 -> 5821194.4 | X15: =X16+X17+X18 -> 5821194.4
A16: B.1.1 | B16: Site Establishment | C16: 0 | D16: 363816 | E16: 86695.251 | F16: 0 | G16: 0 | H16: 0 | I16: 0 | J16: 800 | K16: 398700 | M16: 28168 | N16: 0 | O16: 3337380 | P16: 21000 | Q16: =C16+D16+E16+F16+G16+H16+I16+J16+K16+M16+N16+O16+P16 -> 4236559.3 | R16: 0.03 | S16: 0.08 | T16: 0.1 | U16: =((1+R16)/(1-S16-T16))*Q16 -> 5321531.7 | V16: 0 | X16: =U16+V16+W16 -> 5321531.7
A17: B.1.3 | B17: Design & Engineering | C17: 42558.48 | D17: 0 | E17: 65.715569 | F17: 0 | G17: 0 | H17: 0 | I17: 0 | J17: 0 | K17: 25000 | M17: 14989.92 | N17: 212613.36 | O17: 2562.24 | P17: 100000 | Q17: =C17+D17+E17+F17+G17+H17+I17+J17+K17+M17+N17+O17+P17 -> 397789.72 | R17: 0.03 | S17: 0.08 | T17: 0.1 | U17: =((1+R17)/(1-S17-T17))*Q17 -> 499662.69 | V17: 0 | X17: =U17+V17+W17 -> 499662.69
A18: B.1.4 | B18: Other Fixed Prelims | C18: 0 | D18: 0 | E18: 0 | F18: 0 | G18: 0 | H18: 0 | I18: 0 | J18: 0 | K18: 0 | M18: 0 | N18: 0 | O18: 0 | P18: 0 | Q18: =C18+D18+E18+F18+G18+H18+I18+J18+K18+M18+N18+O18+P18 -> 0 | U18: =((1+R18)/(1-S18-T18))*Q18 -> 0 | X18: =U18+V18+W18 -> 0
A19: B.2 | B19: Time Related Preliminary Costs | C19: =C20+C21+C22+C23 -> 0 | D19: =D20+D21+D22+D23 -> 1587348 | E19: =E20+E21+E22+E23 -> 392394.24 | F19: =F20+F21+F22+F23 -> 0 | G19: =G20+G21+G22+G23 -> 0 | H19: =H20+H21+H22+H23 -> 0 | I19: =I20+I21+I22+I23 -> 0 | J19: =J20+J21+J22+J23 -> 0 | ... P19: =P20+P21+P22+P23 -> 278517 | Q19: =C19+D19+E19+F19+G19+H19+I19+J19+K19+M19+N19+O19+P19 -> 11110109 | U19: =U20+U21+U22+U23 -> 13955380 | X19: =X20+X21+X22+X23 -> 13955380
A20: B2.1 | B20: Supervision | C20: 0 | D20: 0 | E20: 0 | F20: 0 | G20: 0 | H20: 0 | I20: 0 | J20: 0 | K20: 0 | M20: 382017.78 | N20: 7109889.7 | O20: 0 | P20: 0 | Q20: =C20+D20+E20+F20+G20+H20+I20+J20+K20+M20+N20+O20+P20 -> 7491907.4 | R20: 0.03 | S20: 0.08 | T20: 0.1 | U20: =((1+R20)/(1-S20-T20))*Q20 -> 9410566.7 | V20: 0 | X20: =U20+V20+W20 -> 9410566.7
A21: B2.2 | B21: Site Running | C21: 0 | D21: 1587348 | E21: 392394.24 | F21: 0 | G21: 0 | H21: 0 | I21: 0 | J21: 0 | K21: 0 | M21: 0 | N21: 0 | O21: 9000 | P21: 0 | Q21: =C21+D21+E21+F21+G21+H21+I21+J21+K21+M21+N21+O21+P21 -> 1988742.2 | R21: 0.03 | S21: 0.08 | T21: 0.1 | U21: =((1+R21)/(1-S21-T21))*Q21 -> 2498054.3 | V21: 0 | X21: =U21+V21+W21 -> 2498054.3
A22: B2.3 | B22: Bond & Insurance | C22: 0 | D22: 0 | E22: 0 | F22: 0 | G22: 0 | H22: 0 | I22: 0 | J22: 0 | K22: 0 | M22: 0 | N22: 0 | O22: 640092 | P22: 0 | Q22: =C22+D22+E22+F22+G22+H22+I22+J22+K22+M22+N22+O22+P22 -> 640092 | R22: 0.03 | S22: 0.08 | T22: 0.1 | U22: =((1+R22)/(1-S22-T22))*Q22 -> 804018 | V22: 0 | X22: =U22+V22+W22 -> 804018
A23: B2.4 | B23: Other Time Related Prelims | C23: 0 | D23: 0 | E23: 0 | F23: 0 | G23: 0 | H23: 0 | I23: 0 | J23: 0 | K23: 710850 | M23: 0 | N23: 0 | O23: 0 | P23: 278517 | Q23: =C23+D23+E23+F23+G23+H23+I23+J23+K23+M23+N23+O23+P23 -> 989367 | R23: 0.03 | S23: 0.08 | T23: 0.1 | U23: =((1+R23)/(1-S23-T23))*Q23 -> 1242741.5 | V23: 0 | X23: =U23+V23+W23 -> 1242741.5
A25: C | B25: Works | C25: =C26+C27+C28+C29+C30+C31+C32+C33+C34 -> 7356327.5 | D25: =D26+D27+D28+D29+D30+D31+D32+D33+D34 -> 9624904.4 | E25: =E26+E27+E28+E29+E30+E31+E32+E33+E34 -> 8786749.8 | F25: =F26+F27+F28+F29+F30+F31+F32+F33+F34 -> 1169229 | G25: =G26+G27+G28+G29+G30+G31+G32+G33+G34 -> 124966.1 | H25: =H26+H27+H28+H29+H30+H31+H32+H33+H34 -> 594704.98 | I25: =I26+I27+I28+I29+I30+I31+I32+I33+I34 -> 11517888 | J25: =J26+J27+J28+J29+J30+J31+J32+J33+J34 -> 2292676.3 | ... P25: =P26+P27+P28+P29+P30+P31+P32+P33+P34 -> 3943093.4 | Q25: =C25+D25+E25+F25+G25+H25+I25+J25+K25+M25+N25+O25+P25 -> 77510484 | U25: =U26+U27+U28+U29+U30+U31+U32+U33+U34 -> 87999337 | X25: =X26+X27+X28+X29+X30+X31+X32+X33+X34 -> 87999337
A26: C.1 | B26: Dredging | C26: =7481327.48148244-125000 -> 7356327.5 | D26: 0 | E26: 5158218.3 | F26: 0 | G26: 124966.1 | H26: 0 | I26: 0 | J26: 0 | K26: 1032569.4 | M26: 1594757.4 | N26: 3167992.7 | O26: 18119181 | Q26: =C26+D26+E26+F26+G26+H26+I26+J26+K26+M26+N26+O26+P26 -> 36554012 | U26: =((1+R26)/(1-S26-T26))*Q26 -> 36554012 | X26: =U26+V26+W26 -> 36554012
A27: C.2 | B27: Reclamation | C27: 0 | D27: =1862550.69957335+[1]DataForm!$D$27+131826.906885609 -> 4195698.5 | E27: =1060136.33672609+[1]DataForm!$E$27 -> 1784404.5 | F27: 1169229 | G27: 0 | H27: 0 | I27: 0 | J27: 0 | K27: =2815890+[1]DataForm!$K$27 -> 3062771.8 | M27: =181189.285470484+[1]DataForm!$M$27 -> 505625.88 | N27: 285192.73 | O27: 594879.56 | P27: 0 | Q27: =C27+D27+E27+F27+G27+H27+I27+J27+K27+M27+N27+O27+P27 -> 11597802 | R27: 0.03 | S27: 0.08 | T27: 0.1 | U27: =((1+R27)/(1-S27-T27))*Q27 -> 14567971 | X27: =U27+V27+W27 -> 14567971
A28: C.3 | B28: Backfilling/Earthworks | C28: 0 | D28: 0 | E28: 0 | F28: 0 | G28: 0 | H28: 0 | I28: 0 | J28: 0 | K28: 0 | M28: 0 | N28: 0 | O28: 0 | P28: 0 | Q28: =C28+D28+E28+F28+G28+H28+I28+J28+K28+M28+N28+O28+P28 -> 0 | U28: =((1+R28)/(1-S28-T28))*Q28 -> 0 | X28: =U28+V28+W28 -> 0
A29: C.4 | B29: Quay Wall | C29: 0 | D29: 0 | E29: 0 | F29: 0 | G29: 0 | H29: 0 | I29: 0 | J29: 0 | K29: 0 | M29: 0 | N29: 0 | O29: 0 | P29: 0 | Q29: =C29+D29+E29+F29+G29+H29+I29+J29+K29+M29+N29+O29+P29 -> 0 | U29: =((1+R29)/(1-S29-T29))*Q29 -> 0 | X29: =U29+V29+W29 -> 0
A30: C.5 | B30: Rock Works | C30: 0 | D30: 3689010.5 | E30: 1528666.9 | F30: 0 | G30: 0 | H30: 0 | I30: 11517888 | J30: 0 | K30: 745441.98 | M30: 862906.82 | N30: 0 | O30: 524164.75 | P30: 90340.93 | Q30: =C30+D30+E30+F30+G30+H30+I30+J30+K30+M30+N30+O30+P30 -> 18958420 | R30: 0.03 | S30: 0.08 | T30: 0.1 | U30: =((1+R30)/(1-S30-T30))*Q30 -> 23813625 | V30: 0 | X30: =U30+V30+W30 -> 23813625
A31: C.6 | B31: Trenching | C31: 0 | D31: 0 | E31: 0 | F31: 0 | G31: 0 | H31: 0 | I31: 0 | J31: 0 | K31: 0 | M31: 0 | N31: 0 | O31: 0 | P31: 0 | Q31: =C31+D31+E31+F31+G31+H31+I31+J31+K31+M31+N31+O31+P31 -> 0 | U31: =((1+R31)/(1-S31-T31))*Q31 -> 0 | X31: =U31+V31+W31 -> 0
A32: C.7 | B32: Marine Civil | C32: 0 | D32: 539137.32 | E32: 182602.24 | F32: 0 | G32: 0 | H32: 594704.98 | I32: 0 | J32: 2292676.3 | K32: 458210.95 | M32: 861038.34 | N32: 0 | O32: 0 | P32: 12727.864 | Q32: =C32+D32+E32+F32+G32+H32+I32+J32+K32+M32+N32+O32+P32 -> 4941098 | R32: 0.03 | S32: 0.08 | T32: 0.1 | U32: =((1+R32)/(1-S32-T32))*Q32 -> 6206501.2 | X32: =U32+V32+W32 -> 6206501.2
A33: C.8 | B33: Soil Improvement | C33: 0 | D33: 1201058.1 | E33: 132857.89 | F33: 0 | G33: 0 | H33: 0 | I33: 0 | J33: 0 | K33: 0 | M33: 285211.68 | N33: 0 | O33: 0 | P33: 3840024.6 | Q33: =C33+D33+E33+F33+G33+H33+I33+J33+K33+M33+N33+O33+P33 -> 5459152.3 | R33: 0.03 | S33: 0.08 | T33: 0.1 | U33: =((1+R33)/(1-S33-T33))*Q33 -> 6857227.9 | X33: =U33+V33+W33 -> 6857227.9
A34: C.9 | B34: Other Works | C34: 0 | D34: 0 | E34: 0 | F34: 0 | G34: 0 | H34: 0 | I34: 0 | J34: 0 | K34: 0 | M34: 0 | N34: 0 | O34: 0 | P34: 0 | Q34: =C34+D34+E34+F34+G34+H34+I34+J34+K34+M34+N34+O34+P34 -> 0 | U34: =((1+R34)/(1-S34-T34))*Q34 -> 0 | X34: =U34+V34+W34 -> 0
A36: D | B36: Other | C36: =C37+C38 -> 0 | D36: =D37+D38 -> 18499.78 | E36: =E37+E38 -> 5592.7031 | F36: =F37+F38 -> 0 | G36: =G37+G38 -> 0 | H36: =H37+H38 -> 0 | I36: =I37+I38 -> 0 | J36: =J37+J38 -> 0 | ... P36: =P37+P38 -> 0 | Q36: =C36+D36+E36+F36+G36+H36+I36+J36+K36+M36+N36+O36+P36 -> 92294.983 | U36: =U37+U38 -> 129215.49 | X36: =X37+X38 -> 129215.49
A37: D.1 | B37: Provisional Sums | C37: 0 | D37: 0 | E37: 0 | F37: 0 | G37: 0 | H37: 0 | I37: 0 | J37: 0 | K37: 0 | M37: 0 | N37: 0 | O37: 0 | P37: 0 | Q37: =C37+D37+E37+F37+G37+H37+I37+J37+K37+M37+N37+O37+P37 -> 0 | U37: =((1+R37)/(1-S37-T37))*Q37 -> 0 | X37: =U37+V37+W37 -> 0
A38: D.2 | B38: Dayrates | C38: 0 | D38: 18499.78 | E38: 5592.7031 | F38: 0 | G38: 0 | H38: 0 | I38: 0 | J38: 0 | K38: 0 | M38: 68202.5 | N38: 0 | O38: 0 | P38: 0 | Q38: =C38+D38+E38+F38+G38+H38+I38+J38+K38+M38+N38+O38+P38 -> 92294.983 | R38: 0.03 | S38: 0.08 | T38: 0.1843 | U38: =((1+R38)/(1-S38-T38))*Q38 -> 129215.49 | X38: =U38+V38+W38 -> 129215.49
A40: E | B40: Discount | L40: =SUM(F40:K40) -> 0 | Q40: =C40+D40+E40+F40+G40+H40+I40+J40+K40+M40+N40+O40+P40 -> 0 | U40: =((1+R40)/(1-S40-T40))*Q40 -> 0 | X40: =U40+V40+W40 -> 0
B42: Total | C42: =C40+C36+C25+C14+C10 -> 8312319.1 | D42: =D40+D36+D25+D14+D10 -> 12151119 | E42: =E40+E36+E25+E14+E10 -> 10632597 | F42: =F40+F36+F25+F14+F10 -> 1245267.6 | G42: =G40+G36+G25+G14+G10 -> 124966.1 | H42: =H40+H36+H25+H14+H10 -> 594704.98 | I42: =I40+I36+I25+I14+I10 -> 11517888 | J42: =J40+J36+J25+J14+J10 -> 2293476.3 | ... P42: =P40+P36+P25+P14+P10 -> 4892610.3 | Q42: =C42+D42+E42+F42+G42+H42+I42+J42+K42+M42+N42+O42+P42 -> 1.0046306e+08 | U42: =U40+U36+U25+U14+U10 -> 1.168433e+08 | X42: =X40+X36+X25+X14+X10 -> 1.168433e+08

Sheet Equipment_CostEstimators
A1: Detailed Equipment Cost
A2: Cost in [AED] | C2: Internal | K2: External | L2: Total
C3: Internal Equipment | H3: Misc | I3: Personnel
B4: Number of Equipment | C4: D+I | D4: Fixed M&R | E4: Variable M&R | F4: Insurance | G4: Sum internal | H4: Tech OH | I4: Labour | J4: Staff
A5: Marine
A6: CSD | C6: 0 | D6: 0 | E6: 0 | F6: 0 | G6: =C6+D6+E6+F6 -> 0 | H6: 0 | I6: 0 | J6: 0 | K6: 0 | L6: =G6+K6 -> 0
A7: TSHD | C7: 0 | D7: 0 | E7: 0 | F7: 0 | G7: =C7+D7+E7+F7 -> 0 | H7: 0 | I7: 0 | J7: 0 | K7: 0 | L7: =G7+K7 -> 0
A8: BHD | C8: 0 | D8: 0 | E8: 0 | F8: 0 | G8: =C8+D8+E8+F8 -> 0 | H8: 0 | I8: 0 | J8: 0 | K8: 0 | L8: =G8+K8 -> 0
A9: Grab Dredger | C9: 0 | D9: 0 | E9: 0 | F9: 0 | G9: =C9+D9+E9+F9 -> 0 | H9: 0 | I9: 0 | J9: 0 | K9: 0 | L9: =G9+K9 -> 0
A10: Booster | C10: 0 | D10: 0 | E10: 0 | F10: 0 | G10: =C10+D10+E10+F10 -> 0 | H10: 0 | I10: 0 | J10: 0 | K10: 0 | L10: =G10+K10 -> 0
A11: Multicat | C11: 0 | D11: 0 | E11: 0 | F11: 0 | G11: =C11+D11+E11+F11 -> 0 | H11: 0 | I11: 0 | J11: 0 | K11: 0 | L11: =G11+K11 -> 0
A12: Tug | B12: 2 | C12: 0 | D12: 0 | E12: 0 | F12: 0 | G12: =C12+D12+E12+F12 -> 0 | H12: 0 | I12: 0 | J12: 0 | K12: 723696.51 | L12: =G12+K12 -> 723696.51
A13: Crew Boat + Survey | B13: 1 | C13: 21354.72 | D13: 3194.64 | E13: 14643.12 | F13: 3366 | G13: =C13+D13+E13+F13 -> 42558.48 | H13: 2562.24 | I13: 14989.92 | J13: 0 | K13: 0 | L13: =G13+K13 -> 42558.48
A14: Work Barge | C14: 0 | D14: 0 | E14: 0 | F14: 0 | G14: =C14+D14+E14+F14 -> 0 | H14: 0 | I14: 0 | J14: 0 | K14: 0 | L14: =G14+K14 -> 0
A15: Transport Barge | B15: 2 | C15: 0 | D15: 0 | E15: 0 | F15: 0 | G15: =C15+D15+E15+F15 -> 0 | H15: 0 | I15: 0 | J15: 0 | K15: 578957.2 | L15: =G15+K15 -> 578957.2
A16: Other Marine Equipment | C16: 0 | D16: 0 | E16: 0 | F16: 0 | G16: =C16+D16+E16+F16 -> 0 | H16: 0 | I16: 0 | J16: 0 | K16: 0 | L16: =G16+K16 -> 0
A18: Dry earth
A19: Excavator | B19: 7 | G19: =C19+D19+E19+F19 -> 0 | K19: 1400684.2 | L19: =G19+K19 -> 1400684.2
A20: Crawler Crane | B20: 2 | G20: =C20+D20+E20+F20 -> 0 | K20: 1164837.9 | L20: =G20+K20 -> 1164837.9
A21: Bulldozer | B21: 2 | G21: =C21+D21+E21+F21 -> 0 | K21: 330714.46 | L21: =G21+K21 -> 330714.46
A22: Wheelloader | B22: 4 | G22: =C22+D22+E22+F22 -> 0 | K22: 541622.01 | L22: =G22+K22 -> 541622.01
A23: Dumper Truck | B23: 16 | G23: =C23+D23+E23+F23 -> 0 | K23: 1092167.2 | L23: =G23+K23 -> 1092167.2
A24: Fuel Tanker | B24: 1 | G24: =C24+D24+E24+F24 -> 0 | K24: 168000 | L24: =G24+K24 -> 168000
A25: Water Tanker | B25: 1 | G25: =C25+D25+E25+F25 -> 0 | K25: 349782.4 | L25: =G25+K25 -> 349782.4
A26: Compact Roller | B26: 4 | G26: =C26+D26+E26+F26 -> 0 | K26: 1064315.1 | L26: =G26+K26 -> 1064315.1
A27: Trailer | B27: 2 | G27: =C27+D27+E27+F27 -> 0 | K27: 99254.52 | L27: =G27+K27 -> 99254.52
A28: Car/bus/pickup | B28: 5 | G28: =C28+D28+E28+F28 -> 0 | K28: 1257345 | L28: =G28+K28 -> 1257345
A29: Other Dry earth Equipment | G29: =C29+D29+E29+F29 -> 0 | K29: 490043.88 | L29: =G29+K29 -> 490043.88
A31: Other
A32: Other Equipment Cost | G32: =C32+D32+E32+F32 -> 0 | L32: =G32+K32 -> 0
A33: MobDemob Marine Equipment | C33: 21914.4 | D33: 4557.6 | E33: 11904 | F33: 4101.6 | G33: =C33+D33+E33+F33 -> 42477.6 | H33: 3232.8 | I33: 17635.2 | J33: 48507.6 | K33: 132122.88 | L33: =G33+K33 -> 174600.48
A34: MobDemob Dry earth Equipment | C34: 0 | D34: 0 | E34: 0 | F34: 0 | G34: =C34+D34+E34+F34 -> 0 | H34: 0 | I34: 0 | J34: 0 | K34: 334090.88 | L34: =G34+K34 -> 334090.88
A36: Equipment Cost | C36: =C32+C29+C23+C22+C21+C20+C19+C6+C10+C11+C12+C13+C14+C15+C16+C33+C34+C28+C27+C26+C25+C24+C7+C8+C9 -> 43269.12 | D36: =D32+D29+D23+D22+D21+D20+D19+D6+D10+D11+D12+D13+D14+D15+D16+D33+D34+D28+D27+D26+D25+D24+D7+D8+D9 -> 7752.24 | E36: =E32+E29+E23+E22+E21+E20+E19+E6+E10+E11+E12+E13+E14+E15+E16+E33+E34+E28+E27+E26+E25+E24+E7+E8+E9 -> 26547.12 | F36: =F32+F29+F23+F22+F21+F20+F19+F6+F10+F11+F12+F13+F14+F15+F16+F33+F34+F28+F27+F26+F25+F24+F7+F8+F9 -> 7467.6 | G36: =G32+G29+G23+G22+G21+G20+G19+G6+G10+G11+G12+G13+G14+G15+G16+G33+G34+G28+G27+G26+G25+G24+G7+G8+G9 -> 85036.08 | K36: =K32+K29+K23+K22+K21+K20+K19+K6+K10+K11+K12+K13+K14+K15+K16+K33+K34+K28+K27+K26+K25+K24+K9+K8+K7 -> 9727634.1 | L36: =K36+G36 -> 9812670.2 | M36: =IF(L36=L39,"","Not same as equipment cost in tender datafrom!!") -> Not same as equipment cost in tender datafrom!!
C37: =SUM(C36:F36) -> 85036.08
G38: =DataForm!C42 -> 8312319.1 | K38: =DataForm!D42 -> 12151119
K39: Crosscheck: | L39: =DataForm!C42+DataForm!D42 -> 20463438

Sheet Equipment_DredgingEstimators
A1: Detailed Equipment Cost
A2: Cost in [AED] | C2: Internal | K2: External | L2: Total
C3: Internal Equipment | H3: Misc | I3: Personnel
B4: Number of Equipment | C4: D+I | D4: Fixed M&R | E4: Variable M&R | F4: Insurance | G4: Sum internal | H4: Tech OH | I4: Labour | J4: Staff
A5: Marine
A6: CSD | B6: 1 | C6: =2347243.2618049+131826.906885609-8-125000 -> 2354062.2 | D6: 334492.85 | E6: 2815545 | F6: 222026.51 | G6: =C6+D6+E6+F6 -> 5726126.6 | H6: 915819.01 | I6: 905358.57 | J6: 1990806.9 | L6: =G6+K6 -> 5726126.6
A7: TSHD | G7: =C7+D7+E7+F7 -> 0 | L7: =G7+K7 -> 0
A8: BHD | G8: =C8+D8+E8+F8 -> 0 | L8: =G8+K8 -> 0
A9: Grab Dredger | G9: =C9+D9+E9+F9 -> 0 | L9: =G9+K9 -> 0
A10: Booster | G10: =C10+D10+E10+F10 -> 0 | L10: =G10+K10 -> 0
A11: Multicat | B11: 1 | C11: 275140.44 | D11: 62673.885 | E11: 117267.18 | F11: 73772.659 | G11: =C11+D11+E11+F11 -> 528854.16 | H11: 43968.074 | I11: 251280.35 | J11: 151607.88 | L11: =G11+K11 -> 528854.16
A12: Tug | B12: 1 | C12: 857500.99 | D12: 66521.187 | E12: 282038.92 | F12: 211804.95 | G12: =C12+D12+E12+F12 -> 1417866 | H12: 137213.88 | I12: 373312.93 | J12: 975938.06 | L12: =G12+K12 -> 1417866
A13: Crew Boat + Survey | B13: 2 | C13: 288947.64 | D13: 114629.1 | E13: 227505.49 | F13: 55172.895 | G13: =C13+D13+E13+F13 -> 686255.11 | H13: 50950.195 | I13: 365804.01 | J13: 146113.31 | L13: =G13+K13 -> 686255.11
A14: Work Barge | G14: =C14+D14+E14+F14 -> 0 | L14: =G14+K14 -> 0
A15: Transport Barge | G15: =C15+D15+E15+F15 -> 0 | L15: =G15+K15 -> 0
A16: Other Marine Equipment | G16: =C16+D16+E16+F16 -> 0 | L16: =G16+K16 -> 0
A18: Dry earth
A19: Excavator | C19: 2 | G19: =C19+D19+E19+F19 -> 2 | K19: 573464.61 | L19: =G19+K19 -> 573466.61
A20: Crawler Crane | G20: =C20+D20+E20+F20 -> 0 | L20: =G20+K20 -> 0
A21: Bulldozer | C21: 2 | G21: =C21+D21+E21+F21 -> 2 | K21: 955774.36 | L21: =G21+K21 -> 955776.36
A22: Wheelloader | C22: 3 | G22: =C22+D22+E22+F22 -> 3 | K22: 382309.74 | L22: =G22+K22 -> 382312.74
A23: Dumper Truck | C23: 1 | G23: =C23+D23+E23+F23 -> 1 | K23: 380109.05 | L23: =G23+K23 -> 380110.05
A24: Fuel Tanker | G24: =C24+D24+E24+F24 -> 0 | L24: =G24+K24 -> 0
A25: Water Tanker | G25: =C25+D25+E25+F25 -> 0 | L25: =G25+K25 -> 0
A26: Compact Roller | G26: =C26+D26+E26+F26 -> 0 | L26: =G26+K26 -> 0
A27: Trailer | G27: =C27+D27+E27+F27 -> 0 | L27: =G27+K27 -> 0
A28: Car/bus/pickup | G28: =C28+D28+E28+F28 -> 0 | L28: =G28+K28 -> 0
A29: Other Dry earth Equipment | G29: =C29+D29+E29+F29 -> 0 | L29: =G29+K29 -> 0
A31: Other
A32: Other Equipment Cost | G32: =C32+D32+E32+F32 -> 0 | L32: =G32+K32 -> 0
A33: MobDemob Marine Equipment | G33: =C33+D33+E33+F33 -> 0 | L33: =G33+K33 -> 0
A34: MobDemob Dry earth Equipment | G34: =C34+D34+E34+F34 -> 0 | L34: =G34+K34 -> 0
A36: Equipment Cost | C36: =C32+C29+C23+C22+C21+C20+C19+C6+C10+C11+C12+C13+C14+C15+C16+C33+C34+C28+C27+C26+C25+C24+C7+C8+C9 -> 3775659.2 | D36: =D32+D29+D23+D22+D21+D20+D19+D6+D10+D11+D12+D13+D14+D15+D16+D33+D34+D28+D27+D26+D25+D24+D7+D8+D9 -> 578317.02 | E36: =E32+E29+E23+E22+E21+E20+E19+E6+E10+E11+E12+E13+E14+E15+E16+E33+E34+E28+E27+E26+E25+E24+E7+E8+E9 -> 3442356.6 | F36: =F32+F29+F23+F22+F21+F20+F19+F6+F10+F11+F12+F13+F14+F15+F16+F33+F34+F28+F27+F26+F25+F24+F7+F8+F9 -> 562777.02 | G36: =G32+G29+G23+G22+G21+G20+G19+G6+G10+G11+G12+G13+G14+G15+G16+G33+G34+G28+G27+G26+G25+G24+G7+G8+G9 -> 8359109.9 | K36: =K32+K29+K23+K22+K21+K20+K19+K6+K10+K11+K12+K13+K14+K15+K16+K33+K34+K28+K27+K26+K25+K24+K7+K8+K9 -> 2291657.8 | L36: =K36+G36 -> 10650768 | M36: =IF(L36=L39,"","Not same as equipment cost in tender datafrom!!") -> Not same as equipment cost in tender datafrom!!
C37: =SUM(C36:F36) -> 8359109.9
K39: Crosscheck: | L39: =DataForm!C42+DataForm!D42 -> 20463438

Sheet Equipment_Total
A1: Detailed Equipment Cost
A2: Cost in [AED] | C2: Internal | K2: External | L2: Total
C3: Internal Equipment | H3: Misc | I3: Personnel
B4: Number of Equipment | C4: D+I | D4: Fixed M&R | E4: Variable M&R | F4: Insurance | G4: Sum internal | H4: Tech OH | I4: Labour | J4: Staff
A5: Marine
A6: CSD | B6: =Equipment_CostEstimators!B6+Equipment_DredgingEstimators!B6 -> 1 | C6: =Equipment_CostEstimators!C6+Equipment_DredgingEstimators!C6 -> 2354062.2 | D6: =Equipment_CostEstimators!D6+Equipment_DredgingEstimators!D6 -> 334492.85 | E6: =Equipment_CostEstimators!E6+Equipment_DredgingEstimators!E6 -> 2815545 | F6: =Equipment_CostEstimators!F6+Equipment_DredgingEstimators!F6 -> 222026.51 | G6: =C6+D6+E6+F6 -> 5726126.6 | H6: =Equipment_CostEstimators!H6+Equipment_DredgingEstimators!H6 -> 915819.01 | I6: =Equipment_CostEstimators!I6+Equipment_DredgingEstimators!I6 -> 905358.57 | J6: =Equipment_CostEstimators!J6+Equipment_DredgingEstimators!J6 -> 1990806.9 | K6: =Equipment_CostEstimators!K6+Equipment_DredgingEstimators!K6 -> 0 | L6: =G6+K6 -> 5726126.6
A7: TSHD | B7: =Equipment_CostEstimators!B7+Equipment_DredgingEstimators!B7 -> 0 | C7: =Equipment_CostEstimators!C7+Equipment_DredgingEstimators!C7 -> 0 | D7: =Equipment_CostEstimators!D7+Equipment_DredgingEstimators!D7 -> 0 | E7: =Equipment_CostEstimators!E7+Equipment_DredgingEstimators!E7 -> 0 | F7: =Equipment_CostEstimators!F7+Equipment_DredgingEstimators!F7 -> 0 | G7: =C7+D7+E7+F7 -> 0 | H7: =Equipment_CostEstimators!H7+Equipment_DredgingEstimators!H7 -> 0 | I7: =Equipment_CostEstimators!I7+Equipment_DredgingEstimators!I7 -> 0 | J7: =Equipment_CostEstimators!J7+Equipment_DredgingEstimators!J7 -> 0 | K7: =Equipment_CostEstimators!K7+Equipment_DredgingEstimators!K7 -> 0 | L7: =G7+K7 -> 0
A8: BHD | B8: =Equipment_CostEstimators!B8+Equipment_DredgingEstimators!B8 -> 0 | C8: =Equipment_CostEstimators!C8+Equipment_DredgingEstimators!C8 -> 0 | D8: =Equipment_CostEstimators!D8+Equipment_DredgingEstimators!D8 -> 0 | E8: =Equipment_CostEstimators!E8+Equipment_DredgingEstimators!E8 -> 0 | F8: =Equipment_CostEstimators!F8+Equipment_DredgingEstimators!F8 -> 0 | G8: =C8+D8+E8+F8 -> 0 | H8: =Equipment_CostEstimators!H8+Equipment_DredgingEstimators!H8 -> 0 | I8: =Equipment_CostEstimators!I8+Equipment_DredgingEstimators!I8 -> 0 | J8: =Equipment_CostEstimators!J8+Equipment_DredgingEstimators!J8 -> 0 | K8: =Equipment_CostEstimators!K8+Equipment_DredgingEstimators!K8 -> 0 | L8: =G8+K8 -> 0
A9: Grab Dredger | B9: =Equipment_CostEstimators!B9+Equipment_DredgingEstimators!B9 -> 0 | C9: =Equipment_CostEstimators!C9+Equipment_DredgingEstimators!C9 -> 0 | D9: =Equipment_CostEstimators!D9+Equipment_DredgingEstimators!D9 -> 0 | E9: =Equipment_CostEstimators!E9+Equipment_DredgingEstimators!E9 -> 0 | F9: =Equipment_CostEstimators!F9+Equipment_DredgingEstimators!F9 -> 0 | G9: =C9+D9+E9+F9 -> 0 | H9: =Equipment_CostEstimators!H9+Equipment_DredgingEstimators!H9 -> 0 | I9: =Equipment_CostEstimators!I9+Equipment_DredgingEstimators!I9 -> 0 | J9: =Equipment_CostEstimators!J9+Equipment_DredgingEstimators!J9 -> 0 | K9: =Equipment_CostEstimators!K9+Equipment_DredgingEstimators!K9 -> 0 | L9: =G9+K9 -> 0
A10: Booster | B10: =Equipment_CostEstimators!B10+Equipment_DredgingEstimators!B10 -> 0 | C10: =Equipment_CostEstimators!C10+Equipment_DredgingEstimators!C10 -> 0 | D10: =Equipment_CostEstimators!D10+Equipment_DredgingEstimators!D10 -> 0 | E10: =Equipment_CostEstimators!E10+Equipment_DredgingEstimators!E10 -> 0 | F10: =Equipment_CostEstimators!F10+Equipment_DredgingEstimators!F10 -> 0 | G10: =C10+D10+E10+F10 -> 0 | H10: =Equipment_CostEstimators!H10+Equipment_DredgingEstimators!H10 -> 0 | I10: =Equipment_CostEstimators!I10+Equipment_DredgingEstimators!I10 -> 0 | J10: =Equipment_CostEstimators!J10+Equipment_DredgingEstimators!J10 -> 0 | K10: =Equipment_CostEstimators!K10+Equipment_DredgingEstimators!K10 -> 0 | L10: =G10+K10 -> 0
A11: Multicat | B11: =Equipment_CostEstimators!B11+Equipment_DredgingEstimators!B11 -> 1 | C11: =Equipment_CostEstimators!C11+Equipment_DredgingEstimators!C11 -> 275140.44 | D11: =Equipment_CostEstimators!D11+Equipment_DredgingEstimators!D11 -> 62673.885 | E11: =Equipment_CostEstimators!E11+Equipment_DredgingEstimators!E11 -> 117267.18 | F11: =Equipment_CostEstimators!F11+Equipment_DredgingEstimators!F11 -> 73772.659 | G11: =C11+D11+E11+F11 -> 528854.16 | H11: =Equipment_CostEstimators!H11+Equipment_DredgingEstimators!H11 -> 43968.074 | I11: =Equipment_CostEstimators!I11+Equipment_DredgingEstimators!I11 -> 251280.35 | J11: =Equipment_CostEstimators!J11+Equipment_DredgingEstimators!J11 -> 151607.88 | K11: =Equipment_CostEstimators!K11+Equipment_DredgingEstimators!K11 -> 0 | L11: =G11+K11 -> 528854.16
A12: Tug | B12: =Equipment_CostEstimators!B12+Equipment_DredgingEstimators!B12 -> 3 | C12: =Equipment_CostEstimators!C12+Equipment_DredgingEstimators!C12 -> 857500.99 | D12: =Equipment_CostEstimators!D12+Equipment_DredgingEstimators!D12 -> 66521.187 | E12: =Equipment_CostEstimators!E12+Equipment_DredgingEstimators!E12 -> 282038.92 | F12: =Equipment_CostEstimators!F12+Equipment_DredgingEstimators!F12 -> 211804.95 | G12: =C12+D12+E12+F12 -> 1417866 | H12: =Equipment_CostEstimators!H12+Equipment_DredgingEstimators!H12 -> 137213.88 | I12: =Equipment_CostEstimators!I12+Equipment_DredgingEstimators!I12 -> 373312.93 | J12: =Equipment_CostEstimators!J12+Equipment_DredgingEstimators!J12 -> 975938.06 | K12: =Equipment_CostEstimators!K12+Equipment_DredgingEstimators!K12 -> 723696.51 | L12: =G12+K12 -> 2141562.6
A13: Crew Boat + Survey | B13: =Equipment_CostEstimators!B13+Equipment_DredgingEstimators!B13 -> 3 | C13: =Equipment_CostEstimators!C13+Equipment_DredgingEstimators!C13 -> 310302.36 | D13: =Equipment_CostEstimators!D13+Equipment_DredgingEstimators!D13 -> 117823.74 | E13: =Equipment_CostEstimators!E13+Equipment_DredgingEstimators!E13 -> 242148.61 | F13: =Equipment_CostEstimators!F13+Equipment_DredgingEstimators!F13 -> 58538.895 | G13: =C13+D13+E13+F13 -> 728813.59 | H13: =Equipment_CostEstimators!H13+Equipment_DredgingEstimators!H13 -> 53512.435 | I13: =Equipment_CostEstimators!I13+Equipment_DredgingEstimators!I13 -> 380793.93 | J13: =Equipment_CostEstimators!J13+Equipment_DredgingEstimators!J13 -> 146113.31 | K13: =Equipment_CostEstimators!K13+Equipment_DredgingEstimators!K13 -> 0 | L13: =G13+K13 -> 728813.59
A14: Work Barge | B14: =Equipment_CostEstimators!B14+Equipment_DredgingEstimators!B14 -> 0 | C14: =Equipment_CostEstimators!C14+Equipment_DredgingEstimators!C14 -> 0 | D14: =Equipment_CostEstimators!D14+Equipment_DredgingEstimators!D14 -> 0 | E14: =Equipment_CostEstimators!E14+Equipment_DredgingEstimators!E14 -> 0 | F14: =Equipment_CostEstimators!F14+Equipment_DredgingEstimators!F14 -> 0 | G14: =C14+D14+E14+F14 -> 0 | H14: =Equipment_CostEstimators!H14+Equipment_DredgingEstimators!H14 -> 0 | I14: =Equipment_CostEstimators!I14+Equipment_DredgingEstimators!I14 -> 0 | J14: =Equipment_CostEstimators!J14+Equipment_DredgingEstimators!J14 -> 0 | K14: =Equipment_CostEstimators!K14+Equipment_DredgingEstimators!K14 -> 0 | L14: =G14+K14 -> 0
A15: Transport Barge | B15: =Equipment_CostEstimators!B15+Equipment_DredgingEstimators!B15 -> 2 | C15: =Equipment_CostEstimators!C15+Equipment_DredgingEstimators!C15 -> 0 | D15: =Equipment_CostEstimators!D15+Equipment_DredgingEstimators!D15 -> 0 | E15: =Equipment_CostEstimators!E15+Equipment_DredgingEstimators!E15 -> 0 | F15: =Equipment_CostEstimators!F15+Equipment_DredgingEstimators!F15 -> 0 | G15: =C15+D15+E15+F15 -> 0 | H15: =Equipment_CostEstimators!H15+Equipment_DredgingEstimators!H15 -> 0 | I15: =Equipment_CostEstimators!I15+Equipment_DredgingEstimators!I15 -> 0 | J15: =Equipment_CostEstimators!J15+Equipment_DredgingEstimators!J15 -> 0 | K15: =Equipment_CostEstimators!K15+Equipment_DredgingEstimators!K15 -> 578957.2 | L15: =G15+K15 -> 578957.2
A16: Other Marine Equipment | B16: =Equipment_CostEstimators!B16+Equipment_DredgingEstimators!B16 -> 0 | C16: =Equipment_CostEstimators!C16+Equipment_DredgingEstimators!C16 -> 0 | D16: =Equipment_CostEstimators!D16+Equipment_DredgingEstimators!D16 -> 0 | E16: =Equipment_CostEstimators!E16+Equipment_DredgingEstimators!E16 -> 0 | F16: =Equipment_CostEstimators!F16+Equipment_DredgingEstimators!F16 -> 0 | G16: =C16+D16+E16+F16 -> 0 | H16: =Equipment_CostEstimators!H16+Equipment_DredgingEstimators!H16 -> 0 | I16: =Equipment_CostEstimators!I16+Equipment_DredgingEstimators!I16 -> 0 | J16: =Equipment_CostEstimators!J16+Equipment_DredgingEstimators!J16 -> 0 | K16: =Equipment_CostEstimators!K16+Equipment_DredgingEstimators!K16 -> 0 | L16: =G16+K16 -> 0
A18: Dry earth
A19: Excavator | B19: =Equipment_CostEstimators!B19+Equipment_DredgingEstimators!B19 -> 7 | C19: =Equipment_CostEstimators!C19+Equipment_DredgingEstimators!C19 -> 2 | D19: =Equipment_CostEstimators!D19+Equipment_DredgingEstimators!D19 -> 0 | E19: =Equipment_CostEstimators!E19+Equipment_DredgingEstimators!E19 -> 0 | F19: =Equipment_CostEstimators!F19+Equipment_DredgingEstimators!F19 -> 0 | G19: =C19+D19+E19+F19 -> 2 | H19: =Equipment_CostEstimators!H19+Equipment_DredgingEstimators!H19 -> 0 | I19: =Equipment_CostEstimators!I19+Equipment_DredgingEstimators!I19 -> 0 | J19: =Equipment_CostEstimators!J19+Equipment_DredgingEstimators!J19 -> 0 | K19: =Equipment_CostEstimators!K19+Equipment_DredgingEstimators!K19 -> 1974148.8 | L19: =G19+K19 -> 1974150.8
A20: Crawler Crane | B20: =Equipment_CostEstimators!B20+Equipment_DredgingEstimators!B20 -> 2 | C20: =Equipment_CostEstimators!C20+Equipment_DredgingEstimators!C20 -> 0 | D20: =Equipment_CostEstimators!D20+Equipment_DredgingEstimators!D20 -> 0 | E20: =Equipment_CostEstimators!E20+Equipment_DredgingEstimators!E20 -> 0 | F20: =Equipment_CostEstimators!F20+Equipment_DredgingEstimators!F20 -> 0 | G20: =C20+D20+E20+F20 -> 0 | H20: =Equipment_CostEstimators!H20+Equipment_DredgingEstimators!H20 -> 0 | I20: =Equipment_CostEstimators!I20+Equipment_DredgingEstimators!I20 -> 0 | J20: =Equipment_CostEstimators!J20+Equipment_DredgingEstimators!J20 -> 0 | K20: =Equipment_CostEstimators!K20+Equipment_DredgingEstimators!K20 -> 1164837.9 | L20: =G20+K20 -> 1164837.9
A21: Bulldozer | B21: =Equipment_CostEstimators!B21+Equipment_DredgingEstimators!B21 -> 2 | C21: =Equipment_CostEstimators!C21+Equipment_DredgingEstimators!C21 -> 2 | D21: =Equipment_CostEstimators!D21+Equipment_DredgingEstimators!D21 -> 0 | E21: =Equipment_CostEstimators!E21+Equipment_DredgingEstimators!E21 -> 0 | F21: =Equipment_CostEstimators!F21+Equipment_DredgingEstimators!F21 -> 0 | G21: =C21+D21+E21+F21 -> 2 | H21: =Equipment_CostEstimators!H21+Equipment_DredgingEstimators!H21 -> 0 | I21: =Equipment_CostEstimators!I21+Equipment_DredgingEstimators!I21 -> 0 | J21: =Equipment_CostEstimators!J21+Equipment_DredgingEstimators!J21 -> 0 | K21: =Equipment_CostEstimators!K21+Equipment_DredgingEstimators!K21 -> 1286488.8 | L21: =G21+K21 -> 1286490.8
A22: Wheelloader | B22: =Equipment_CostEstimators!B22+Equipment_DredgingEstimators!B22 -> 4 | C22: =Equipment_CostEstimators!C22+Equipment_DredgingEstimators!C22 -> 3 | D22: =Equipment_CostEstimators!D22+Equipment_DredgingEstimators!D22 -> 0 | E22: =Equipment_CostEstimators!E22+Equipment_DredgingEstimators!E22 -> 0 | F22: =Equipment_CostEstimators!F22+Equipment_DredgingEstimators!F22 -> 0 | G22: =C22+D22+E22+F22 -> 3 | H22: =Equipment_CostEstimators!H22+Equipment_DredgingEstimators!H22 -> 0 | I22: =Equipment_CostEstimators!I22+Equipment_DredgingEstimators!I22 -> 0 | J22: =Equipment_CostEstimators!J22+Equipment_DredgingEstimators!J22 -> 0 | K22: =Equipment_CostEstimators!K22+Equipment_DredgingEstimators!K22 -> 923931.75 | L22: =G22+K22 -> 923934.75
A23: Dumper Truck | B23: =Equipment_CostEstimators!B23+Equipment_DredgingEstimators!B23 -> 16 | C23: =Equipment_CostEstimators!C23+Equipment_DredgingEstimators!C23 -> 1 | D23: =Equipment_CostEstimators!D23+Equipment_DredgingEstimators!D23 -> 0 | E23: =Equipment_CostEstimators!E23+Equipment_DredgingEstimators!E23 -> 0 | F23: =Equipment_CostEstimators!F23+Equipment_DredgingEstimators!F23 -> 0 | G23: =C23+D23+E23+F23 -> 1 | H23: =Equipment_CostEstimators!H23+Equipment_DredgingEstimators!H23 -> 0 | I23: =Equipment_CostEstimators!I23+Equipment_DredgingEstimators!I23 -> 0 | J23: =Equipment_CostEstimators!J23+Equipment_DredgingEstimators!J23 -> 0 | K23: =Equipment_CostEstimators!K23+Equipment_DredgingEstimators!K23 -> 1472276.3 | L23: =G23+K23 -> 1472277.3
A24: Fuel Tanker | B24: =Equipment_CostEstimators!B24+Equipment_DredgingEstimators!B24 -> 1 | C24: =Equipment_CostEstimators!C24+Equipment_DredgingEstimators!C24 -> 0 | D24: =Equipment_CostEstimators!D24+Equipment_DredgingEstimators!D24 -> 0 | E24: =Equipment_CostEstimators!E24+Equipment_DredgingEstimators!E24 -> 0 | F24: =Equipment_CostEstimators!F24+Equipment_DredgingEstimators!F24 -> 0 | G24: =C24+D24+E24+F24 -> 0 | H24: =Equipment_CostEstimators!H24+Equipment_DredgingEstimators!H24 -> 0 | I24: =Equipment_CostEstimators!I24+Equipment_DredgingEstimators!I24 -> 0 | J24: =Equipment_CostEstimators!J24+Equipment_DredgingEstimators!J24 -> 0 | K24: =Equipment_CostEstimators!K24+Equipment_DredgingEstimators!K24 -> 168000 | L24: =G24+K24 -> 168000
A25: Water Tanker | B25: =Equipment_CostEstimators!B25+Equipment_DredgingEstimators!B25 -> 1 | C25: =Equipment_CostEstimators!C25+Equipment_DredgingEstimators!C25 -> 0 | D25: =Equipment_CostEstimators!D25+Equipment_DredgingEstimators!D25 -> 0 | E25: =Equipment_CostEstimators!E25+Equipment_DredgingEstimators!E25 -> 0 | F25: =Equipment_CostEstimators!F25+Equipment_DredgingEstimators!F25 -> 0 | G25: =C25+D25+E25+F25 -> 0 | H25: =Equipment_CostEstimators!H25+Equipment_DredgingEstimators!H25 -> 0 | I25: =Equipment_CostEstimators!I25+Equipment_DredgingEstimators!I25 -> 0 | J25: =Equipment_CostEstimators!J25+Equipment_DredgingEstimators!J25 -> 0 | K25: =Equipment_CostEstimators!K25+Equipment_DredgingEstimators!K25 -> 349782.4 | L25: =G25+K25 -> 349782.4
A26: Compact Roller | B26: =Equipment_CostEstimators!B26+Equipment_DredgingEstimators!B26 -> 4 | C26: =Equipment_CostEstimators!C26+Equipment_DredgingEstimators!C26 -> 0 | D26: =Equipment_CostEstimators!D26+Equipment_DredgingEstimators!D26 -> 0 | E26: =Equipment_CostEstimators!E26+Equipment_DredgingEstimators!E26 -> 0 | F26: =Equipment_CostEstimators!F26+Equipment_DredgingEstimators!F26 -> 0 | G26: =C26+D26+E26+F26 -> 0 | H26: =Equipment_CostEstimators!H26+Equipment_DredgingEstimators!H26 -> 0 | I26: =Equipment_CostEstimators!I26+Equipment_DredgingEstimators!I26 -> 0 | J26: =Equipment_CostEstimators!J26+Equipment_DredgingEstimators!J26 -> 0 | K26: =Equipment_CostEstimators!K26+Equipment_DredgingEstimators!K26 -> 1064315.1 | L26: =G26+K26 -> 1064315.1
A27: Trailer | B27: =Equipment_CostEstimators!B27+Equipment_DredgingEstimators!B27 -> 2 | C27: =Equipment_CostEstimators!C27+Equipment_DredgingEstimators!C27 -> 0 | D27: =Equipment_CostEstimators!D27+Equipment_DredgingEstimators!D27 -> 0 | E27: =Equipment_CostEstimators!E27+Equipment_DredgingEstimators!E27 -> 0 | F27: =Equipment_CostEstimators!F27+Equipment_DredgingEstimators!F27 -> 0 | G27: =C27+D27+E27+F27 -> 0 | H27: =Equipment_CostEstimators!H27+Equipment_DredgingEstimators!H27 -> 0 | I27: =Equipment_CostEstimators!I27+Equipment_DredgingEstimators!I27 -> 0 | J27: =Equipment_CostEstimators!J27+Equipment_DredgingEstimators!J27 -> 0 | K27: =Equipment_CostEstimators!K27+Equipment_DredgingEstimators!K27 -> 99254.52 | L27: =G27+K27 -> 99254.52
A28: Car/bus/pickup | B28: =Equipment_CostEstimators!B28+Equipment_DredgingEstimators!B28 -> 5 | C28: =Equipment_CostEstimators!C28+Equipment_DredgingEstimators!C28 -> 0 | D28: =Equipment_CostEstimators!D28+Equipment_DredgingEstimators!D28 -> 0 | E28: =Equipment_CostEstimators!E28+Equipment_DredgingEstimators!E28 -> 0 | F28: =Equipment_CostEstimators!F28+Equipment_DredgingEstimators!F28 -> 0 | G28: =C28+D28+E28+F28 -> 0 | H28: =Equipment_CostEstimators!H28+Equipment_DredgingEstimators!H28 -> 0 | I28: =Equipment_CostEstimators!I28+Equipment_DredgingEstimators!I28 -> 0 | J28: =Equipment_CostEstimators!J28+Equipment_DredgingEstimators!J28 -> 0 | K28: =Equipment_CostEstimators!K28+Equipment_DredgingEstimators!K28 -> 1257345 | L28: =G28+K28 -> 1257345
A29: Other Dry earth Equipment | B29: =Equipment_CostEstimators!B29+Equipment_DredgingEstimators!B29 -> 0 | C29: =Equipment_CostEstimators!C29+Equipment_DredgingEstimators!C29 -> 0 | D29: =Equipment_CostEstimators!D29+Equipment_DredgingEstimators!D29 -> 0 | E29: =Equipment_CostEstimators!E29+Equipment_DredgingEstimators!E29 -> 0 | F29: =Equipment_CostEstimators!F29+Equipment_DredgingEstimators!F29 -> 0 | G29: =C29+D29+E29+F29 -> 0 | H29: =Equipment_CostEstimators!H29+Equipment_DredgingEstimators!H29 -> 0 | I29: =Equipment_CostEstimators!I29+Equipment_DredgingEstimators!I29 -> 0 | J29: =Equipment_CostEstimators!J29+Equipment_DredgingEstimators!J29 -> 0 | K29: =Equipment_CostEstimators!K29+Equipment_DredgingEstimators!K29 -> 490043.88 | L29: =G29+K29 -> 490043.88
A31: Other
A32: Other Equipment Cost | B32: =Equipment_CostEstimators!B32+Equipment_DredgingEstimators!B32 -> 0 | C32: =Equipment_CostEstimators!C32+Equipment_DredgingEstimators!C32 -> 0 | D32: =Equipment_CostEstimators!D32+Equipment_DredgingEstimators!D32 -> 0 | E32: =Equipment_CostEstimators!E32+Equipment_DredgingEstimators!E32 -> 0 | F32: =Equipment_CostEstimators!F32+Equipment_DredgingEstimators!F32 -> 0 | G32: =C32+D32+E32+F32 -> 0 | H32: =Equipment_CostEstimators!H32+Equipment_DredgingEstimators!H32 -> 0 | I32: =Equipment_CostEstimators!I32+Equipment_DredgingEstimators!I32 -> 0 | J32: =Equipment_CostEstimators!J32+Equipment_DredgingEstimators!J32 -> 0 | K32: =Equipment_CostEstimators!K32+Equipment_DredgingEstimators!K32 -> 0 | L32: =G32+K32 -> 0
A33: MobDemob Marine Equipment | B33: =Equipment_CostEstimators!B33+Equipment_DredgingEstimators!B33 -> 0 | C33: =Equipment_CostEstimators!C33+Equipment_DredgingEstimators!C33 -> 21914.4 | D33: =Equipment_CostEstimators!D33+Equipment_DredgingEstimators!D33 -> 4557.6 | E33: =Equipment_CostEstimators!E33+Equipment_DredgingEstimators!E33 -> 11904 | F33: =Equipment_CostEstimators!F33+Equipment_DredgingEstimators!F33 -> 4101.6 | G33: =C33+D33+E33+F33 -> 42477.6 | H33: =Equipment_CostEstimators!H33+Equipment_DredgingEstimators!H33 -> 3232.8 | I33: =Equipment_CostEstimators!I33+Equipment_DredgingEstimators!I33 -> 17635.2 | J33: =Equipment_CostEstimators!J33+Equipment_DredgingEstimators!J33 -> 48507.6 | K33: =Equipment_CostEstimators!K33+Equipment_DredgingEstimators!K33 -> 132122.88 | L33: =G33+K33 -> 174600.48
A34: MobDemob Dry earth Equipment | B34: =Equipment_CostEstimators!B34+Equipment_DredgingEstimators!B34 -> 0 | C34: =Equipment_CostEstimators!C34+Equipment_DredgingEstimators!C34 -> 0 | D34: =Equipment_CostEstimators!D34+Equipment_DredgingEstimators!D34 -> 0 | E34: =Equipment_CostEstimators!E34+Equipment_DredgingEstimators!E34 -> 0 | F34: =Equipment_CostEstimators!F34+Equipment_DredgingEstimators!F34 -> 0 | G34: =C34+D34+E34+F34 -> 0 | H34: =Equipment_CostEstimators!H34+Equipment_DredgingEstimators!H34 -> 0 | I34: =Equipment_CostEstimators!I34+Equipment_DredgingEstimators!I34 -> 0 | J34: =Equipment_CostEstimators!J34+Equipment_DredgingEstimators!J34 -> 0 | K34: =Equipment_CostEstimators!K34+Equipment_DredgingEstimators!K34 -> 334090.88 | L34: =G34+K34 -> 334090.88
A36: Equipment Cost | C36: =C32+C29+C23+C22+C21+C20+C19+C6+C10+C11+C12+C13+C14+C15+C16+C33+C34+C28+C27+C26+C25+C24+C9+C8+C7 -> 3818928.4 | D36: =D32+D29+D23+D22+D21+D20+D19+D6+D10+D11+D12+D13+D14+D15+D16+D33+D34+D28+D27+D26+D25+D24+D9+D8+D7 -> 586069.26 | E36: =E32+E29+E23+E22+E21+E20+E19+E6+E10+E11+E12+E13+E14+E15+E16+E33+E34+E28+E27+E26+E25+E24+E9+E8+E7 -> 3468903.7 | F36: =F32+F29+F23+F22+F21+F20+F19+F6+F10+F11+F12+F13+F14+F15+F16+F33+F34+F28+F27+F26+F25+F24+F9+F8+F7 -> 570244.62 | G36: =G32+G29+G23+G22+G21+G20+G19+G6+G10+G11+G12+G13+G14+G15+G16+G33+G34+G28+G27+G26+G25+G24+G9+G8+G7 -> 8444146 | K36: =K32+K29+K23+K22+K21+K20+K19+K6+K10+K11+K12+K13+K14+K15+K16+K33+K34+K28+K27+K26+K25+K24+K9+K8+K7 -> 12019292 | L36: =K36+G36 -> 20463438 | M36: =IF(L36=L39,"","Not same as equipment cost in tender datafrom!!")
C37: =SUM(C36:F36) -> 8444146
K39: Crosscheck: | L39: =DataForm!C42+DataForm!D42 -> 20463438

Sheet List
A1: Countries | C1: Sub / Main Contract | E1: Contract Form
A2: Afghanistan | C2: Main Contract | E2: 1. FIDIC | F2: Blue Book | G2: Red Book | H2: Yellow Book | I2: Silver Book | J2: Beige Book | K2: White Book | L2: Orange Book | M2: Gold Book | N2: Conditions of Contracts for works of Civil Engineering Construction | O2: Conditions of Subcontract for Construction 2010
A3: Akrotiri and Dhekelia (UK) | C3: Subcontract | E3: 2. Engineering and Construction Contract (ECC) | F3: Option A | G3: Option B | H3: Option C | I3: Option D | J3: Option E | K3: Option F
A4: Aland Islands (Finland) | E4: 3. Institution of Civil Engineers (ICE) | F4: ICE Conditions of Contract Measurement Version | G4: ICE Conditions of Contract Design and Construct | H4: ICE Conditions of Contracts Minor Works | I4: ICE Conditions of Contract Term Version | J4: ICE Conditions of Contract Ground Investigation | K4: Agreement for Consultancy Work in respect of Domestic or Small Works
A5: Albania | E5: 4. Bespoke forms supplied by Clients | F5: ADNOC Conditions of Contract | G5: ARAMCO Conditions of Contract | H5: GAZCO Conditions of Contract | I5: TDIC Conditions of Contract | J5: ABU DHABI PORTS Conditions of Contract | K5: NPCC Conditions of Contract | L5: PETROFAC Conditions of Contract | M5: SAIPEM Conditions of Contract | N5: TECTON Conditions of Contract | O5: ADMA-OPCO Conditions of Contract | P5: TECNIMONT Conditions of Contract | Q5: MUSANADA Conditions of Contract | R5: ABU DHABI STANDARD FORM DESIGN & BUILD Conditions of Contract
A6: Algeria | E6: 5. Bahraini Government conditions of contract | F6: Building And Engineering Works | G6: Engineering Consultancy Services | H6: Quantity Surveying Consultancy Services | I6: Minor Works, Supply of Materials, Supply of Equipment's, Supply of Human Resources and Maintenance & Repair
A7: American Samoa (USA)
A8: Andorra
A9: Angola | C9: Payment method | E9: Tender Status | G9: Reasons to regret
A10: Anguilla (UK) | C10: Lump Sum | E10: Pre-Tender | G10: No Time
A11: Antigua and Barbuda | C11: Remeasurable | E11: Declined | G11: No Equipment Available
A12: Argentina | E12: Submitted | G12: No Suitable Equipment
A13: Armenia | E13: Submitted and in Negotiation | G13: SOW is Not Relevant
A14: Aruba (Netherlands) | C14: YesNo | E14: Closed for Post-Tender | G14: Not the Right Region
A15: Ascension Island (UK) | C15: Yes | E15: Post-Tender | G15: Too Small
A16: Australia | C16: No | E16: Closed | G16: Too Large
A17: Austria | E17: Awarded | G17: Other
A18: Azerbaijan | C18: Estimators | E18: Lost
A19: Bahamas | C19: Rommel Adarlo | E19: Iema11
A20: Bahrain | C20: Satyajit Maheshgauti | E20: On Hold
A21: Bangladesh | C21: Vaibhav Mahta | E21: Cancelled
A22: Barbados | C22: Sachin Sarjerao Patil | E22: Unknown
A23: Belarus | C23: Yannick Willems
A24: Belgium | C24: Pieter Steverlynck
A25: Belize | C25: Guus Derksen
A26: Benin
A27: Bermuda (UK)
A28: Bhutan | C28: ProposalManagers
A29: Bolivia | C29: Christopher Mendoza
A30: Bonaire (Netherlands) | C30: Senthil Kumar Arjunan
A31: Bosnia and Herzegovina
A32: Botswana
A33: Brazil
A34: British Indian Ocean Territory (UK)
A35: British Virgin Islands (UK)
A36: Brunei
A37: Bulgaria
A38: Burkina Faso
A39: Burundi
A40: Cabo Verde
A41: Cambodia
A42: Cameroon
... A254: Zimbabwe

Sheet Internal Equipment split
A1: Internal Equipment Split up
A3: Category | C3: Dredgers without var M&R (Not operational) | O3: Boosters without var M&R | S3: Multicat | AA3: Tug | AL3: TowingTug | AR3: CrewBoat | AW3: Survey | BC3: Other
A4: Name | C4: Al Sadr | D4: Al Mirfa | E4: Kattouf | F4: Umm El Zemoul | G4: Al Khatem | H4: Al Hamra | I4: Umm Al Anber | J4: Dredge II | K4: Al Shahama | L4: Jananah | M4: Embarka | O4: Booster 1 | P4: Booster 2 | Q4: Booster 3 | S4: Al Khatab 1 | T4: Belyryar | U4: M13, M16, M17 | V4: M8, M9, M10 | W4: M11, M12 | X4: M4, M5 | Y4: M6 | AA4: Al Kadeh, Bu Sharah, Damen yard | AB4: T6 | AC4: T3 | AD4: T4, T5 | AE4: T7, T8 | AF4: T1 | AG4: P11, P12 | AH4: P13 | AI4: P8 P9 P10 | AJ4: P2 P5 P7 | AL4: Ramhan | AM4: Al Adham, Opale, Pearly | AN4: Jamouh | AO4: Abu al sayaaf | AP4: Camar | AR4: Grandweld | AS4: Sea Falcon II | AT4: Lulu10 Lulu11 Lulu12 | AU4: Ardeem | AW4: S4 | AX4: S6 | AY4: S5 | AZ4: S1 | BA4: S2 | BC4: Safeena | BD4: Stan Lift 65 A2 | BE4: Remah Fuel Barge | BF4: Anood | BG4: Areela | BH4: Delma 9 Delma 10 | BI4: Delma 7 Delma 12 | BJ4: Isamu, Adora, Bellona | BK4: Estalla, Fidelia | BL4: Elata, Delfina | BM4: Delma 11 | BN4: Delma 3 | BO4: S1 barge
A5: Internal Equipment | B5: D+I | C5: 0.511598 | D5: 0.4650991 | E5: 0.4650991 | F5: 0.37037093 | G5: 0.37037093 | H5: 0.37037093 | I5: 0.33195972 | J5: 0.322398 | K5: 0.33337618 | L5: 0.264138 | M5: 0.326741 | O5: 0.318904 | P5: 0.3930887 | Q5: 0.4756286 | S5: 0.29426267 | T5: 0.22072787 | U5: 0.31166034 | V5: 0.219184 | W5: 0.1459772 | X5: 0.094008999 | Y5: 0.078738345 | AA5: 0.33977614 | AB5: 0.23210701 | AC5: 0.17535823 | AD5: 0.17924668 | AE5: 0.23178562 | AF5: 0.11289097 | AG5: 0.089490617 | AH5: 0.18383002 | AI5: 0.074564651 | AJ5: 0.044138239 | AL5: 0.24917179 | AM5: 0.28104691 | AN5: 0.28104691 | AO5: 0.28104691 | AP5: 0.18532707 | AR5: 0.2596314 | AS5: 0.19351864 | AT5: 0.21493548 | AU5: 0.12169349 | AW5: 0.353484 | AX5: 0.20322804 | AY5: 0.16145859 | AZ5: 0.17038438 | BA5: 0.17038438 | BC5: 0.51047883 | BD5: 0.18553813 | BE5: 0.370455 | BF5: 0.32085327 | BG5: 0.50457615 | BH5: 0.28185816 | BI5: 0.29181641 | BJ5: 0.46077649 | BK5: 0.41645257 | BL5: 0.44211212 | BM5: 0.70862868 | BN5: 0.4118354 | BO5: 0.33269549
B6: Fixed M&R | C6: 0.028374 | D6: 0.028905476 | E6: 0.028905476 | F6: 0.052779543 | G6: 0.052779543 | H6: 0.052779543 | I6: 0.037320598 | J6: 0.042647 | K6: 0.02499393 | L6: 0.024175 | M6: 0.021498 | O6: 0.037301 | P6: 0.0241448 | Q6: 0.028812 | S6: 0.045326966 | T6: 0.045907277 | U6: 0.070992707 | V6: 0.097551172 | W6: 0.089334956 | X6: 0.18282538 | Y6: 0.089224596 | AA6: 0.026783644 | AB6: 0.042963186 | AC6: 0.046501519 | AD6: 0.047532659 | AE6: 0.056263817 | AF6: 0.059009794 | AG6: 0.1006385 | AH6: 0.056334341 | AI6: 0.13744941 | AJ6: 0.1249228 | AL6: 0.029456355 | AM6: 0.020664094 | AN6: 0.020664094 | AO6: 0.020664094 | AP6: 0.022814899 | AR6: 0.053229188 | AS6: 0.13472502 | AT6: 0.0042296773 | AU6: 0.011090333 | AW6: 0.052874421 | AX6: 0.032245504 | AY6: 0.033966904 | AZ6: 0.032704892 | BA6: 0.032704892 | BC6: 0.010641187 | BD6: 0.07431654 | BE6: 0.043606129 | BF6: 0.044573108 | BG6: 0.051636521 | BH6: 0.1537214 | BI6: 0.066653011 | BJ6: 0.39534642 | BK6: 0.4399191 | BL6: 0.40684018 | BM6: 0.028047978 | BN6: 0.40202413 | BO6: 0.57216741
B7: Var M&R | C7: 0 | D7: 0 | E7: 0 | F7: 0 | G7: 0 | H7: 0 | I7: 0 | J7: 0 | K7: 0 | L7: 0 | M7: 0 | O7: 0 | P7: 0 | Q7: 0 | S7: 0.079773673 | T7: 0.11989534 | U7: 0.13283227 | V7: 0.15016861 | W7: 0.25155083 | X7: 0.16693124 | Y7: 0.10112121 | AA7: 0.11186738 | AB7: 0.19973157 | AC7: 0.22064118 | AD7: 0.20335942 | AE7: 0.091460193 | AF7: 0.22387284 | AG7: 0.31338891 | AH7: 0.10710378 | AI7: 0.175194 | AJ7: 0.19646209 | AL7: 0.1630375 | AM7: 0.092137998 | AN7: 0.092137998 | AO7: 0.092137998 | AP7: 0.09664883 | AR7: 0.071013458 | AS7: 0.16755267 | AT7: 0.31407216 | AU7: 0.26066745 | AW7: 0.24236185 | AX7: 0.32390075 | AY7: 0.34077186 | AZ7: 0.24466396 | BA7: 0.24466396 | BC7: 0.09799725 | BD7: 0.35246531 | BE7: 0.031493295 | BF7: 0.071869742 | BG7: 0.096628164 | BH7: 0.19654602 | BI7: 0.27729026 | BJ7: 0 | BK7: 0 | BL7: 0 | BM7: 0 | BN7: 0 | BO7: 0
B8: Insurance | C8: 0.099359 | D8: 0.10780983 | E8: 0.10780983 | F8: 0.035033508 | G8: 0.035033508 | H8: 0.035033508 | I8: 0.06582025 | J8: 0.020695 | K8: 0.031785138 | L8: 0.05189 | M8: 0.069528 | O8: 0.043984 | P8: 0.0707895 | Q8: 0.1133608 | S8: 0.073734953 | T8: 0.041326542 | U8: 0.083564643 | V8: 0.04324105 | W8: 0.02831527 | X8: 0.019074177 | Y8: 0.010998466 | AA8: 0.081004915 | AB8: 0.03974798 | AC8: 0.028368151 | AD8: 0.028997196 | AE8: 0.066372687 | AF8: 0.012419703 | AG8: 0.024479088 | AH8: 0.034737991 | AI8: 0.01870214 | AJ8: 0.016110442 | AL8: 0.087785102 | AM8: 0.077236495 | AN8: 0.077236495 | AO8: 0.077236495 | AP8: 0.057047626 | AR8: 0.071363249 | AS8: 0.045372981 | AT8: 0.061053032 | AU8: 0.025527237 | AW8: 0.055706241 | AX8: 0.019548444 | AY8: 0.020549242 | AZ8: 0.024395226 | BA8: 0.024395226 | BC8: 0.059712172 | BD8: 0.031008091 | BE8: 0.053142292 | BF8: 0.085834234 | BG8: 0.013885975 | BH8: 0.060745271 | BI8: 0.056438952 | BJ8: 0.086443782 | BK8: 0.086195206 | BL8: 0.093614293 | BM8: 0.20589044 | BN8: 0.12870781 | BO8: 0.037702018
A10: Misc | B10: TechOh | C10: 0.13709 | D10: 0.12835977 | E10: 0.12835977 | F10: 0.14450685 | G10: 0.14450685 | H10: 0.14450685 | I10: 0.14757928 | J10: 0.111274 | K10: 0.11241556 | L10: 0.105507 | M10: 0.112039 | O10: 0.164067 | P10: 0.1597487 | Q10: 0.1431453 | S10: 0.049857699 | T10: 0.032556394 | U10: 0.049804038 | V10: 0.048771691 | W10: 0.042985557 | X10: 0.047845741 | Y10: 0.051625162 | AA10: 0.050609285 | AB10: 0.05143114 | AC10: 0.050803095 | AD10: 0.051929619 | AE10: 0.058426496 | AF10: 0.044576117 | AG10: 0.051807167 | AH10: 0.067492088 | AI10: 0.047370965 | AJ10: 0.046149942 | AL10: 0.051287522 | AM10: 0.055036556 | AN10: 0.055036556 | AO10: 0.055036556 | AP10: 0.031726716 | AR10: 0.053354776 | AS10: 0.04732698 | AT10: 0.028564807 | AU10: 0.026537293 | AW10: 0.042398025 | AX10: 0.02520555 | AY10: 0.026519183 | AZ10: 0.029825174 | BA10: 0.029825174 | BC10: 0.052649899 | BD10: 0.044392917 | BE10: 0.062116882 | BF10: 0.062286061 | BG10: 0.051833507 | BH10: 0.053453443 | BI10: 0.048964804 | BJ10: 0.057433308 | BK10: 0.057433122 | BL10: 0.057433412 | BM10: 0.057432897 | BN10: 0.05743266 | BO10: 0.057435087
A12: Labour | B12: Labour | C12: 0.051811215 | D12: 0.069676043 | E12: 0.069676043 | F12: 0.10259556 | G12: 0.10259556 | H12: 0.10259556 | I12: 0.10776291 | J12: 0.17206483 | K12: 0.17016398 | L12: 0.18961512 | M12: 0.16524666 | O12: 0.14493309 | P12: 0.11715488 | Q12: 0.079511665 | S12: 0.095465663 | T12: 0.11270684 | U12: 0.17485737 | V12: 0.21964281 | W12: 0.22001763 | X12: 0.24366002 | Y12: 0.33278414 | AA12: 0.081808893 | AB12: 0.16831976 | AC12: 0.1855034 | AD12: 0.18961681 | AE12: 0.1922372 | AF12: 0.21222502 | AG12: 0.10108639 | AH12: 0.13243409 | AI12: 0.13152402 | AJ12: 0.13765799 | AL12: 0.087956353 | AM12: 0.099414213 | AN12: 0.099414213 | AO12: 0.099414213 | AP12: 0.12722315 | AR12: 0.49140793 | AS12: 0.18913583 | AT12: 0.37714484 | AU12: 0.5544842 | AW12: 0.25317547 | AX12: 0.39587171 | AY12: 0.41673421 | AZ12: 0.49802637 | BA12: 0.49802637 | BC12: 0.067346534 | BD12: 0.31227901 | BE12: 0.15466668 | BF12: 0.086974929 | BG12: 0.067705878 | BH12: 0.057878183 | BI12: 0.059055674 | BJ12: 0 | BK12: 0 | BL12: 0 | BM12: 0 | BN12: 0 | BO12: 0
A14: Staff | B14: Staff | C14: 0.17176886 | D14: 0.20014978 | E14: 0.20014978 | F14: 0.29471362 | G14: 0.29471362 | H14: 0.29471362 | I14: 0.30955724 | J14: 0.33092101 | K14: 0.32726522 | L14: 0.36467432 | M14: 0.30494752 | O14: 0.29081083 | P14: 0.23507335 | Q14: 0.15954157 | S14: 0.36157837 | T14: 0.42687974 | U14: 0.17628863 | V14: 0.22144066 | W14: 0.22181855 | X14: 0.24565445 | Y14: 0.33550808 | AA14: 0.30814974 | AB14: 0.26569936 | AC14: 0.29282442 | AD14: 0.29931761 | AE14: 0.30345399 | AF14: 0.33500556 | AG14: 0.31910934 | AH14: 0.4180677 | AI14: 0.41519481 | AJ14: 0.4345585 | AL14: 0.33130538 | AM14: 0.37446373 | AN14: 0.37446373 | AO14: 0.37446373 | AP14: 0.47921171 | AR14: 0 | AS14: 0.22236789 | AT14: 0 | AU14: 0 | AW14: 0 | AX14: 0 | AY14: 0 | AZ14: 0 | BA14: 0 | BC14: 0.20117413 | BD14: 0 | BE14: 0.28451973 | BF14: 0.32760865 | BG14: 0.2137338 | BH14: 0.19579753 | BI14: 0.19978089 | BJ14: 0 | BK14: 0 | BL14: 0 | BM14: 0 | BN14: 0 | BO14: 0

Sheet DatabaseInput
A1: TenderNumber | B1: TenderRevision | C1: TenderNumber-TenderRevision | D1: Mob_Equipment_Internal | E1: Mob_Equipment_External | F1: Mob_Fuel | G1: Mob_Materials_Pipeline | H1: Mob_Materials_Teeth | I1: Mob_Materials_Steel | J1: Mob_Materials_Rock | K1: Mob_Materials_Concrete | L1: Mob_Materials_Other | M1: Mob_Staff | N1: Mob_Labourer | O1: Mob_Misc | P1: Mob_Subcontractor | Q1: Mob_Risk% | R1: Mob_Overhead% | S1: Mob_Profit% | T1: Mob_DirectTax | U1: Mob_IndirectTax | V1: Demob_Equipment_Internal | W1: Demob_Equipment_External | X1: Demob_Fuel | Y1: Demob_Materials_Pipeline | Z1: Demob_Materials_Teeth | AA1: Demob_Materials_Steel | AB1: Demob_Materials_Rock | AC1: Demob_Materials_Concrete | AD1: Demob_Materials_Other | AE1: Demob_Staff | AF1: Demob_Labourer | AG1: Demob_Misc | AH1: Demob_Subcontractor | AI1: Demob_Risk% | AJ1: Demob_Overhead% | AK1: Demob_Profit% | AL1: Demob_DirectTax | AM1: Demob_InDirectTax | AN1: OfficeSetUp_Equipment_Internal | AO1: OfficeSetUp_Equipment_External | AP1: OfficeSetUp_Fuel | AQ1: OfficeSetUp_Materials_Pipeline | AR1: OfficeSetUp_Materials_Teeth | AS1: OfficeSetUp_Materials_Steel | AT1: OfficeSetUp_Materials_Rock | AU1: OfficeSetUp_Materials_Concrete | AV1: OfficeSetUp_Materials_Other | AW1: OfficeSetUp_Staff | AX1: OfficeSetUp_Labourer | AY1: OfficeSetUp_Misc | AZ1: OfficeSetUp_SubContractor | BA1: OfficeSetUp_Risk% | BB1: OfficeSetUp_Overhead% | BC1: OfficeSetUp_Profit% | BD1: OfficeSetUp_DirectTax | BE1: OfficeSetUp_InDirectTax | BF1: Design_Equipment_Internal | BG1: Design_Equipment_External | BH1: Design_Fuel | BI1: Design_Materials_Pipeline | BJ1: Design_Materials_Teeth | BK1: Design_Materials_Steel | BL1: Design_Materials_Rock | BM1: Design_Materials_Concrete | BN1: Design_Materials_Other | BO1: Design_Staff | BP1: Design_Labourers | BQ1: Design_Misc | BR1: Design_SubContractor | BS1: Design_Risk% | BT1: Design_Overhead% | BU1: Design_Profit% | BV1: Design_DirectTax | BW1: Design_InDirectTax | BX1: OtherFixedPrelims_Equipment_Internal | BY1: OtherFixedPrelims_Equipment_External | BZ1: OtherFixedPrelims_Fuel | CA1: OtherFixedPrelims_Materials_Pipeline | CB1: OtherFixedPrelims_Materials_Teeth | CC1: OtherFixedPrelims_Materials_Steel | CD1: OtherFixedPrelims_Materials_Rock | CE1: OtherFixedPrelims_Materials_Concrete | CF1: OtherFixedPrelims_Materials_Other | CG1: OtherFixedPrelims_Staff | CH1: OtherFixedPrelims_Labourer | CI1: OtherFixedPrelims_Misc | CJ1: OtherFixedPrelims_SubContractor | CK1: OtherFixedPrelims_Risk% | CL1: OtherFixedPrelims_Overhead% | CM1: OtherFixedPrelims_Profit% | CN1: OtherFixedPrelims_DirectTax | CO1: OtherFixedPrelims_InDirectTax | CP1: Supervision_Equipment_Internal | CQ1: Supervision_Equipment_External | CR1: Supervision_Fuel | CS1: Supervision_Materials_Pipeline | CT1: Supervision_Materials_Teeth | CU1: Supervision_Materials_Steel | CV1: Supervision_Materials_Rock | CW1: Supervision_Materials_Concrete | CX1: Supervision_Materials_Other | CY1: Supervision_Staff | CZ1: Supervision_Labourer | DA1: Supervision_Misc | DB1: Supervision_SubContractor | DC1: Supervision_Risk% | DD1: Supervision_Overhead% | DE1: Supervision_Profit% | DF1: Supervision_DirectTax | DG1: Supervision_InDirectTax | DH1: SiteRunning_Equipment_Internal | DI1: SiteRunning_Equipment_External | DJ1: SiteRunning_Fuel | DK1: SiteRunning_Materials_Pipeline | DL1: SiteRunning_Materials_Teeth | DM1: SiteRunning_Materials_Steel | DN1: SiteRunning_Materials_Rock | DO1: SiteRunning_Materials_Concrete | DP1: SiteRunning_Materials_Other | DQ1: SiteRunning_Staff | DR1: SiteRunning_Labourer | DS1: SiteRunning_Misc | DT1: SiteRunning_SubContractor | DU1: SiteRunning_Risk% | DV1: SiteRunning_Overhead% | DW1: SiteRunning_Profit% | DX1: SiteRunning_DirectTax | DY1: SiteRunning_InDirectTax | DZ1: BondInsurance_Equipment_Internal | EA1: BondInsurance_Equipment_External | EB1: BondInsurance_Fuel | EC1: BondInsurance_Materials_Pipeline | ED1: BondInsurance_Materials_Teeth | EE1: BondInsurance_Materials_Steel | EF1: BondInsurance_Materials_Rock | EG1: BondInsurance_Materials_Concrete | EH1: BondInsurance_Materials_Other | EI1: BondInsurance_Staff | EJ1: BondInsurance_Labourer | EK1: BondInsurance_Misc | EL1: BondInsurance_SubContractor | EM1: BondInsurance_Risk% | EN1: BondInsurance_Overhead% | EO1: BondInsurance_Profit% | EP1: BondInsurance_DirectTax | EQ1: BondInsurance_InDirectTax | ER1: OtherTimePrelim_Equipment_Internal | ES1: OtherTimePrelim_Equipment_External | ET1: OtherTimePrelims_Fuel | EU1: OtherTimePrelims_Materials_Pipeline | EV1: OtherTimePrelims_Materials_Teeth | EW1: OtherTimePrelims_Materials_Steel | EX1: OtherTimePrelims_Materials_Rock | EY1: OtherTimePrelims_Materials_Concrete | EZ1: OtherTimePrelims_Materials_Other | FA1: OtherTimePrelim_Staff | FB1: OtherTimePrelim_Labourer | FC1: OtherTimePrelim_Misc | FD1: OtherTimePrelims_SubContractor | FE1: OtherTimePrelim_Risk% | FF1: OtherTimePrelim_Overhead% | FG1: OtherTimePrelim_Profit% | FH1: OtherTimePrelim_DirectTax | FI1: OtherTimePrelim_InDirectTax | FJ1: Dredging_Equipment_Internal | FK1: Dredging_Equipment_External | FL1: Dredging_Fuel | FM1: Dredging_Materials_Pipeline | FN1: Dredging_Materials_Teeth | FO1: Dredging_Materials_Steel | FP1: Dredging_Materials_Rock | FQ1: Dredging_Materials_Concrete | FR1: Dredging_Materials_Other | FS1: Dredging_Staff | FT1: Dredging_Labourer | FU1: Dredging_Misc | FV1: Dredging_SubContractor | FW1: Dredging_Risk% | FX1: Dredging_Overhead% | FY1: Dredging_Profit% | FZ1: Dredging_DirectTax | GA1: Dredging_InDirectTax | GB1: Reclamation_Equipment_Internal | GC1: Reclamation_Equipment_External | GD1: Reclamation_Fuel | GE1: Reclamation_Materials_Pipeline | GF1: Reclamation_Materials_Teeth | GG1: Reclamation_Materials_Steel | GH1: Reclamation_Materials_Rock | GI1: Reclamation_Materials_Concrete | GJ1: Reclamation_Materials_Other | GK1: Reclamation_Staff | GL1: Reclamation_Labourer | GM1: Reclamation_Misc | GN1: Reclamation_Subcontractor | GO1: Reclamation_Risk% | GP1: Reclamation_Overhead% | GQ1: Reclamation_Profit% | GR1: Reclamation_DirectTax | GS1: Reclamation_InDirectTax | GT1: Backfilling_Equipment_Internal | GU1: Backfilling_Equipment_External | GV1: Backfilling_Fuel | GW1: Backfilling_Materials_Pipeline | GX1: Backfilling_Materials_Teeth | GY1: Backfilling_Materials_Steel | GZ1: Backfilling_Materials_Rock | HA1: Backfilling_Materials_Concrete | HB1: Backfilling_Materials_Other | HC1: Backfilling_Staff | HD1: Backfilling_Labourer | HE1: Backfilling_Misc | HF1: Backfilling_Subcontractor | HG1: Backfilling_Risk% | HH1: Backfilling_Overhead% | HI1: Backfilling_Profit% | HJ1: Backfilling_DirectTax | HK1: Backfilling_InDirectTax | HL1: QuayWall_Equipment_Internal | HM1: QuayWall_Equipment_External | HN1: QuayWall_Fuel | HO1: QuayWall_Materials_Pipeline | HP1: QuayWall_Materials_Teeth | HQ1: QuayWall_Materials_Steel | HR1: QuayWall_Materials_Rock | HS1: QuayWall_Materials_Concrete | HT1: QuayWall_Materials_Other | HU1: QuayWall_Staff | HV1: QuayWall_Labourer | HW1: QuayWall_Misc | HX1: QuayWall_SubContractor | HY1: QuayWall_Risk% | HZ1: QuayWall_Overhead% | IA1: QuayWall_Profit% | IB1: QuayWall_DirectTax | IC1: QuayWall_InDirectTax | ID1: RockWorks_Equipment_Internal | IE1: RockWorks_Equipment_External | IF1: RockWorks_Fuel | IG1: RockWorks_Materials_Pipeline | IH1: RockWorks_Materials_Teeth | II1: RockWorks_Materials_Steel | IJ1: RockWorks_Materials_Rock | IK1: RockWorks_Materials_Concrete | IL1: RockWorks_Materials_Other | IM1: RockWorks_Staff | IN1: RockWorks_Labourer | IO1: RockWorks_Misc | IP1: RockWorks_SubContractor | IQ1: RockWorks_Risk% | IR1: RockWorks_Overhead% | IS1: RockWorks_Profit% | IT1: RockWorks_DirectTax | IU1: RockWorks_InDirectTax | IV1: Trenching_Equipment_Internal | IW1: Trenching_Equipment_External | IX1: Trenching_Fuel | IY1: Trenching_Materials_Pipeline | IZ1: Trenching_Materials_Teeth | JA1: Trenching_Materials_Steel | JB1: Trenching_Materials_Rock | JC1: Trenching_Materials_Concrete | JD1: Trenching_Materials_Other | JE1: Trenching_Staff | JF1: Trenching_Labourer | JG1: Trenching_Misc | JH1: Trenching_SubContractor | JI1: Trenching_Risk% | JJ1: Trenching_Overhead% | JK1: Trenching_Profit% | JL1: Trenching_DirectTax | JM1: Trenching_InDirectTax | JN1: MarineCivil_Equipment_Internal | JO1: MarineCivil_Equipment_External | JP1: MarineCivil_Fuel | JQ1: MarineCivil_Materials_Pipeline | JR1: MarineCivil_Materials_Teeth | JS1: MarineCivil_Materials_Steel | JT1: MarineCivil_Materials_Rock | JU1: MarineCivil_Materials_Concrete | JV1: MarineCivil_Materials_Other | JW1: MarineCivil_Staff | JX1: MarineCivil_Labourer | JY1: MarineCivil_Misc | JZ1: MarineCivil_SubContractor | KA1: MarineCivil_Risk% | KB1: MarineCivil_Overhead% | KC1: MarineCivil_Profit% | KD1: MarineCivil_DirectTax | KE1: MarineCivil_InDirectTax | KF1: SoilImpr_Equipment_Internal | KG1: SoilImpr_Equipment_External | KH1: SoilImpr_Fuel | KI1: SoilImprovement_Materials_Pipeline | KJ1: SoilImprovement_Materials_Teeth | KK1: SoilImprovement_Materials_Steel | KL1: SoilImprovement_Materials_Rock | KM1: SoilImprovement_Materials_Concrete | KN1: SoilImprovement_Materials_Other | KO1: SoilImpr_Staff | KP1: SoilImpr_Labourer | KQ1: SoilImpr_Misc | KR1: SoilImpr_SubContractor | KS1: SoilImpr_Risk% | KT1: SoilImpr_Overhead% | KU1: SoilImpr_Profit% | KV1: SoilImpr_DirectTax | KW1: SoilImpr_InDirectTax | KX1: OtherWorks_Equipment_Internal | KY1: OtherWorks_Equipment_External | KZ1: OtherWorks_Fuel | LA1: OtherWorks_Materials_Pipeline | LB1: OtherWorks_Materials_Teeth | LC1: OtherWorks_Materials_Steel | LD1: OtherWorks_Materials_Rock | LE1: OtherWorks_Materials_Concrete | LF1: OtherWorks_Materials_Other | LG1: OtherWorks_Staff | LH1: OtherWorks_Labourer | LI1: OtherWorks_Misc | LJ1: OtherWorks_SubContractor | LK1: OtherWorks_Risk% | LL1: OtherWorks_Overhead% | LM1: OtherWorks_Profit% | LN1: OtherWorks_DirectTax | LO1: OtherWorks_InDirectTax | LP1: ProvSum_Equipment_Internal | LQ1: ProvSum_Equipment_External | LR1: ProvSum_Fuel | LS1: ProvSum_Materials_Pipeline | LT1: ProvSum_Materials_Teeth | LU1: ProvSum_Materials_Steel | LV1: ProvSum_Materials_Rock | LW1: ProvSum_Materials_Concrete | LX1: ProvSum_Materials_Other | LY1: ProvSum_Staff | LZ1: ProvSum_Labourer | MA1: ProvSum_Misc | MB1: ProvSum_SubContractor | MC1: ProvSum_Risk% | MD1: ProvSum_OVerhead% | ME1: ProvSum_Profit% | MF1: ProvSum_DirectTax | MG1: ProvSum_InDirectTax | MH1: DayRates_Equipment_Internal | MI1: DayRates_Equipment_External | MJ1: DayRates_Fuel | MK1: DayRates_Materials_Pipeline | ML1: DayRates_Materials_Teeth | MM1: DayRates_Materials_Steel | MN1: DayRates_Materials_Rock | MO1: DayRates_Materials_Concrete | MP1: DayRates_Materials_Other | MQ1: DayRates_Staff | MR1: DayRates_Labourer | MS1: DayRates_Misc | MT1: Dayrates_SubContractor | MU1: DayRates_Risk% | MV1: DayRates_Overhead% | MW1: DayRates_Profit% | MX1: DayRates_DirectTax | MY1: DayRates_InDirectTax | MZ1: Discount_Equipment_Internal | NA1: Discount_Equipment_External | NB1: Discount_Fuel | NC1: Discount_Materials_Pipeline | ND1: Discount_Materials_Teeth | NE1: Discount_Materials_Steel | NF1: Discount_Materials_Rock | NG1: Discount_Materials_Concrete | NH1: Discount_Materials_Other | NI1: Discount_Staff | NJ1: Discount_Labourers | NK1: Discount_Misc | NL1: Discount_SubContractor | NM1: Discount_Risk% | NN1: Discount_Overhead% | NO1: Discount_Profit% | NP1: Discount_DirectTax | NQ1: Discount_InDirectTax | NR1: Equipment_Internal_CSD_DI | NS1: Equipment_Internal_TSHD_DI | NT1: Equipment_Internal_BHD_DI | NU1: Equipment_Internal_GD_DI | NV1: Equipment_Internal_Booster_DI | NW1: Equipment_Internal_Multicat_DI | NX1: Equipment_Internal_Tug_DI | NY1: Equipment_Internal_SpeedBoatSurvey_DI | NZ1: Equipment_Internal_WorkBarge_DI | OA1: Equipment_Internal_TransportBarge_DI | OB1: Equipment_Internal_OtherMarine_DI | OC1: Equipment_Internal_Excavator_DI | OD1: Equipment_Internal_CrawlerCrane_DI | OE1: Equipment_Internal_Bulldozer_DI | OF1: Equipment_Internal_Wheelloader_DI | OG1: Equipment_Internal_DumperTruck_DI | OH1: Equipment_Internal_FuelTanker_DI | OI1: Equipment_Internal_WaterTanker_DI | OJ1: Equipment_Internal_CompactRoller_DI | OK1: Equipment_Internal_Trailer_DI | OL1: Equipment_Internal_CarBusPickup_DI | OM1: Equipment_Internal_OtherDryEarth_DI | ON1: Equipment_Internal_MobDemobMarine_DI | OO1: Equipment_Internal_MobDemobDryearth_DI | OP1: Equipment_Internal_OtherEquipment_DI | OQ1: Equipment_Internal_CSD_FixedMR | OR1: Equipment_Internal_TSHD_FixedMR | OS1: Equipment_Internal_BHD_FixedMR | OT1: Equipment_Internal_GD_FixedMR | OU1: Equipment_Internal_Booster_FixedMR | OV1: Equipment_Internal_Multicat_FixedMR | OW1: Equipment_Internal_Tug_FixedMR | OX1: Equipment_Internal_SpeedBoatSurvey_FixedMR | OY1: Equipment_Internal_WorkBarge_FixedMR | OZ1: Equipment_Internal_TransportBarge_FixedMR | PA1: Equipment_Internal_OtherMarine_FixedMR | PB1: Equipment_Internal_Excavator_FixedMR | PC1: Equipment_Internal_CrawlerCrane_FixedMR | PD1: Equipment_Internal_Bulldozer_FixedMR | PE1: Equipment_Internal_Wheelloader_FixedMR | PF1: Equipment_Internal_DumperTruck_FixedMR | PG1: Equipment_Internal_FuelTanker_FixedMR | PH1: Equipment_Internal_WaterTanker_FixedMR | PI1: Equipment_Internal_CompactRoller_FixedMR | PJ1: Equipment_Internal_Trailer_FixedMR | PK1: Equipment_Internal_CarBusPickup_FixedMR | PL1: Equipment_Internal_OtherDryEarth_FixedMR | PM1: Equipment_Internal_MobDemobMarine_FixedMR | PN1: Equipment_Internal_MobDemobDryearth_FixedMR | PO1: Equipment_Internal_OtherEquipment_FixedMR | PP1: Equipment_Internal_CSD_VariableMR | PQ1: Equipment_Internal_TSHD_VariableMR | PR1: Equipment_Internal_BHD_VariableMR | PS1: Equipment_Internal_GD_VariableMR | PT1: Equipment_Internal_Booster_VariableMR | PU1: Equipment_Internal_Multicat_VariableMR | PV1: Equipment_Internal_Tug_VariableMR | PW1: Equipment_Internal_SpeedBoatSurvey_VariableMR | PX1: Equipment_Internal_WorkBarge_VariableMR | PY1: Equipment_Internal_TransportBarge_VariableMR | PZ1: Equipment_Internal_OtherMarine_VariableMR | QA1: Equipment_Internal_Excavator_VariableMR | QB1: Equipment_Internal_CrawlerCrane_VariableMR | QC1: Equipment_Internal_Bulldozer_VariableMR | QD1: Equipment_Internal_Wheelloader_VariableMR | QE1: Equipment_Internal_DumperTruck_VariableMR | QF1: Equipment_Internal_FuelTanker_VariableMR | QG1: Equipment_Internal_WaterTanker_VariableMR | QH1: Equipment_Internal_CompactRoller_VariableMR | QI1: Equipment_Internal_Trailer_VariableMR | QJ1: Equipment_Internal_CarBusPickup_VariableMR | QK1: Equipment_Internal_OtherDryEarth_VariableMR | QL1: Equipment_Internal_MobDemobMarine_VariableMR | QM1: Equipment_Internal_MobDemobDryearth_VariableMR | QN1: Equipment_Internal_OtherEquipment_VariableMR | QO1: Equipment_Internal_CSD_Insurance | QP1: Equipment_Internal_TSHD_Insurance | QQ1: Equipment_Internal_BHD_Insurance | QR1: Equipment_Internal_GD_Insurance | QS1: Equipment_Internal_Booster_Insurance | QT1: Equipment_Internal_Multicat_Insurance | QU1: Equipment_Internal_Tug_Insurance | QV1: Equipment_Internal_SpeedBoatSurvey_Insurance | QW1: Equipment_Internal_WorkBarge_Insurance | QX1: Equipment_Internal_TransportBarge_Insurance | QY1: Equipment_Internal_OtherMarine_Insurance | QZ1: Equipment_Internal_Excavator_Insurance | RA1: Equipment_Internal_CrawlerCrane_Insurance | RB1: Equipment_Internal_Bulldozer_Insurance | RC1: Equipment_Internal_Wheelloader_Insurance | RD1: Equipment_Internal_DumperTruck_Insurance | RE1: Equipment_Internal_FuelTanker_Insurance | RF1: Equipment_Internal_WaterTanker_Insurance | RG1: Equipment_Internal_CompactRoller_Insurance | RH1: Equipment_Internal_Trailer_Insurance | RI1: Equipment_Internal_CarBusPickup_Insurance | RJ1: Equipment_Internal_OtherDryEarth_Insurance | RK1: Equipment_Internal_MobDemobMarine_Insurance | RL1: Equipment_Internal_MobDemobDryearth_Insurance | RM1: Equipment_Internal_OtherEquipment_Insurance | RN1: Equipment_External_CSD | RO1: Equipment_External_TSHD | RP1: Equipment_External_BHD | RQ1: Equipment_External_GD | RR1: Equipment_External_Booster | RS1: Equipment_External_Multicat | RT1: Equipment_External_Tug | RU1: Equipment_External_SpeedBoatSurvey | RV1: Equipment_External_WorkBarge | RW1: Equipment_External_TransportBarge | RX1: Equipment_External_OtherMarine | RY1: Equipment_External_Excavator | RZ1: Equipment_External_CrawlerCrane | SA1: Equipment_External_Bulldozer | SB1: Equipment_External_Wheelloader | SC1: Equipment_External_DumperTruck | SD1: Equipment_External_FuelTanker | SE1: Equipment_External_WaterTanker | SF1: Equipment_External_CompactRoller | SG1: Equipment_External_Trailer | SH1: Equipment_External_CarBusPickup | SI1: Equipment_External_OtherDryEarth | SJ1: Equipment_External_MobDemobMarine | SK1: Equipment_External_MobDemobDryearth | SL1: Equipment_External_OtherEquipment | SM1: Equipment_Total_CSD_Number | SN1: Equipment_Total_TSHD_Number | SO1: Equipment_Total_BHD_Number | SP1: Equipment_Total_GD_Number | SQ1: Equipment_Total_Booster_Number | SR1: Equipment_Total_Multicat_Number | SS1: Equipment_Total_Tug_Number | ST1: Equipment_Total_SpeedBoatSurvey_Number | SU1: Equipment_Total_WorkBarge_Number | SV1: Equipment_Total_TransportBarge_Number | SW1: Equipment_Total_OtherMarine_Number | SX1: Equipment_Total_Excavator_Number | SY1: Equipment_Total_CrawlerCrane_Number | SZ1: Equipment_Total_Bulldozer_Number | TA1: Equipment_Total_Wheelloader_Number | TB1: Equipment_Total_DumperTruck_Number | TC1: Equipment_Total_FuelTanker_Number | TD1: Equipment_Total_WaterTanker_Number | TE1: Equipment_Total_CompactRoller_Number | TF1: Equipment_Total_Trailer_Number | TG1: Equipment_Total_CarBusPickup_Number | TH1: Equipment_Total_OtherDryEarth_Number | TI1: Equipment_Total_MobDemobMarine_Number | TJ1: Equipment_Total_MobDemobDryearth_Number | TK1: Equipment_Total_OtherEquipment_Number | TL1: Equipment_Internal_CSD_TechOH | TM1: Equipment_Internal_TSHD_TechOH | TN1: Equipment_Internal_BHD_TechOH | TO1: Equipment_Internal_GD_TechOH | TP1: Equipment_Internal_Booster_TechOH | TQ1: Equipment_Internal_Multicat_TechOH | TR1: Equipment_Internal_Tug_TechOH | TS1: Equipment_Internal_Survey_TechOH | TT1: Equipment_Internal_WorkBarge_TechOH | TU1: Equipment_Internal_TransportBarge_TechOH | TV1: Equipment_Internal_OtherMarine_TechOH | TW1: Equipment_Internal_Excavator_TechOH | TX1: Equipment_Internal_CrawlerCrane_TechOH | TY1: Equipment_Internal_Bulldozer_TechOH | TZ1: Equipment_Internal_Wheelloader_TechOH | UA1: Equipment_Internal_DumperTruck_TechOH | UB1: Equipment_Total_FuelTanker_TechOH | UC1: Equipment_Total_WaterTanker_TechOH | UD1: Equipment_Total_CompactRoller_TechOH | UE1: Equipment_Total_Trailer_TechOH | UF1: Equipment_Total_CarBusPickup_TechOH | UG1: Equipment_Internal_OtherDryEarth_TechOH | UH1: Equipment_Internal_MobDemobMarine_TechOH | UI1: Equipment_Internal_MobDemobDryearth_TechOH | UJ1: Equipment_Internal_OtherEquipment_TechOH | UK1: Equipment_Internal_CSD_Labour | UL1: Equipment_Internal_TSHD_Labour | UM1: Equipment_Internal_BHD_Labour | UN1: Equipment_Internal_GD_Labour | UO1: Equipment_Internal_Booster_Labour | UP1: Equipment_Internal_Multicat_Labour | UQ1: Equipment_Internal_Tug_Labour | UR1: Equipment_Internal_Survey_Labour | US1: Equipment_Internal_WorkBarge_Labour | UT1: Equipment_Internal_TransportBarge_Labour | UU1: Equipment_Internal_OtherMarine_Labour | UV1: Equipment_Internal_Excavator_Labour | UW1: Equipment_Internal_CrawlerCrane_Labour | UX1: Equipment_Internal_Bulldozer_Labour | UY1: Equipment_Internal_Wheelloader_Labour | UZ1: Equipment_Internal_DumperTruck_Labour | VA1: Equipment_Total_FuelTanker_Labour | VB1: Equipment_Total_WaterTanker_Labour | VC1: Equipment_Total_CompactRoller_Labour | VD1: Equipment_Total_Trailer_Labour | VE1: Equipment_Total_CarBusPickup_Labour | VF1: Equipment_Internal_OtherDryEarth_Labour | VG1: Equipment_Internal_MobDemobMarine_Labour | VH1: Equipment_Internal_MobDemobDryearth_Labour | VI1: Equipment_Internal_OtherEquipment_Labour | VJ1: Equipment_Internal_CSD_Staff | VK1: Equipment_Internal_TSHD_Staff | VL1: Equipment_Internal_BHD_Staff | VM1: Equipment_Internal_GD_Staff | VN1: Equipment_Internal_Booster_Staff | VO1: Equipment_Internal_Multicat_Staff | VP1: Equipment_Internal_Tug_Staff | VQ1: Equipment_Internal_Survey_Staff | VR1: Equipment_Internal_WorkBarge_Staff | VS1: Equipment_Internal_TransportBarge_Staff | VT1: Equipment_Internal_OtherMarine_Staff | VU1: Equipment_Internal_Excavator_Staff | VV1: Equipment_Internal_CrawlerCrane_Staff | VW1: Equipment_Internal_Bulldozer_Staff | VX1: Equipment_Internal_Wheelloader_Staff | VY1: Equipment_Internal_DumperTruck_Staff | VZ1: Equipment_Total_FuelTanker_Staff | WA1: Equipment_Total_WaterTanker_Staff | WB1: Equipment_Total_CompactRoller_Staff | WC1: Equipment_Total_Trailer_Staff | WD1: Equipment_Total_CarBusPickup_Staff | WE1: Equipment_Internal_OtherDryEarth_Staff | WF1: Equipment_Internal_MobDemobMarine_Staff | WG1: Equipment_Internal_MobDemobDryearth_Staff | WH1: Equipment_Internal_OtherEquipment_Staff
A2: =TenderInfo!B4 -> 1743-01 | B2: =IF(TenderInfo!B5 = "","",TenderInfo!B5) -> 0 | C2: =A2&"-"&B2 -> 1743-01-0 | D2: =DataForm!C11 -> 565050.9 | E2: =DataForm!D11 -> 291308.83 | F2: =DataForm!E11 -> 831312.11 | G2: =DataForm!F11 -> 45623.131 | H2: =DataForm!G11 -> 0 | I2: =DataForm!H11 -> 0 | J2: =DataForm!I11 -> 0 | K2: =DataForm!J11 -> 0 | L2: =DataForm!K11 -> 113678.05 | M2: =DataForm!N11 -> 457963.25 | N2: =DataForm!M11 -> 209495.73 | O2: =DataForm!O11 -> 2079666.6 | P2: =DataForm!P11 -> 365946.09 | Q2: =DataForm!R11 -> 0.03 | R2: =DataForm!S11 -> 0.08 | S2: =DataForm!T11 -> 0.1 | T2: =DataForm!V11 -> 0 | U2: =DataForm!W11 -> 0 | V2: =DataForm!C12 -> 348382.2 | W2: =DataForm!D12 -> 265241.78 | X2: =DataForm!E12 -> 529786.91 | Y2: =DataForm!F12 -> 30415.421 | Z2: =DataForm!G12 -> 0 | AA2: =DataForm!H12 -> 0 | AB2: =DataForm!I12 -> 0 | AC2: =DataForm!J12 -> 0 | AD2: =DataForm!K12 -> 75785.365 | AE2: =DataForm!N12 -> 261887.55 | AF2: =DataForm!M12 -> 127907.02 | AG2: =DataForm!O12 -> 332322.54 | AH2: =DataForm!P12 -> 184053.73 | AI2: =DataForm!R12 -> 0.03 | AJ2: =DataForm!S12 -> 0.08 | AK2: =DataForm!T12 -> 0.1 | AL2: =DataForm!V12 -> 0 | AM2: =DataForm!W12 -> 0 | AN2: =DataForm!C16 -> 0 | AO2: =DataForm!D16 -> 363816 | AP2: =DataForm!E16 -> 86695.251 | AQ2: =DataForm!F16 -> 0 | AR2: =DataForm!G16 -> 0 | AS2: =DataForm!H16 -> 0 | AT2: =DataForm!I16 -> 0 | AU2: =DataForm!J16 -> 800 | AV2: =DataForm!K16 -> 398700 | AW2: =DataForm!N16 -> 0 | AX2: =DataForm!M16 -> 28168 | AY2: =DataForm!O16 -> 3337380 | AZ2: =DataForm!P16 -> 21000 | BA2: =DataForm!R16 -> 0.03 | BB2: =DataForm!S16 -> 0.08 | BC2: =DataForm!T16 -> 0.1 | BD2: =DataForm!V16 -> 0 | BE2: =DataForm!W16 -> 0 | BF2: =DataForm!C17 -> 42558.48 | BG2: =DataForm!D17 -> 0 | BH2: =DataForm!E17 -> 65.715569 | BI2: =DataForm!F17 -> 0 | BJ2: =DataForm!G17 -> 0 | BK2: =DataForm!H17 -> 0 | BL2: =DataForm!I17 -> 0 | BM2: =DataForm!J17 -> 0 | BN2: =DataForm!K17 -> 25000 | BO2: =DataForm!N17 -> 212613.36 | BP2: =DataForm!M17 -> 14989.92 | BQ2: =DataForm!O17 -> 2562.24 | BR2: =DataForm!P17 -> 100000 | BS2: =DataForm!R17 -> 0.03 | BT2: =DataForm!S17 -> 0.08 | BU2: =DataForm!T17 -> 0.1 | BV2: =DataForm!V17 -> 0 | BW2: =DataForm!W17 -> 0 | BX2: =DataForm!C18 -> 0 | BY2: =DataForm!D18 -> 0 | BZ2: =DataForm!E18 -> 0 | CA2: =DataForm!F18 -> 0 | CB2: =DataForm!G18 -> 0 | CC2: =DataForm!H18 -> 0 | CD2: =DataForm!I18 -> 0 | CE2: =DataForm!J18 -> 0 | CF2: =DataForm!K18 -> 0 | CG2: =DataForm!N18 -> 0 | CH2: =DataForm!M18 -> 0 | CI2: =DataForm!O18 -> 0 | CJ2: =DataForm!P18 -> 0 | CK2: =DataForm!R18 -> 0 | CL2: =DataForm!S18 -> 0 | CM2: =DataForm!T18 -> 0 | CN2: =DataForm!V18 -> 0 | CO2: =DataForm!W18 -> 0 | CP2: =DataForm!C20 -> 0 | CQ2: =DataForm!D20 -> 0 | CR2: =DataForm!E20 -> 0 | CS2: =DataForm!F20 -> 0 | CT2: =DataForm!G20 -> 0 | CU2: =DataForm!H20 -> 0 | CV2: =DataForm!I20 -> 0 | CW2: =DataForm!J20 -> 0 | CX2: =DataForm!K20 -> 0 | CY2: =DataForm!N20 -> 7109889.7 | CZ2: =DataForm!M20 -> 382017.78 | DA2: =DataForm!O20 -> 0 | DB2: =DataForm!P20 -> 0 | DC2: =DataForm!R20 -> 0.03 | DD2: =DataForm!S20 -> 0.08 | DE2: =DataForm!T20 -> 0.1 | DF2: =DataForm!V20 -> 0 | DG2: =DataForm!W20 -> 0 | DH2: =DataForm!C21 -> 0 | DI2: =DataForm!D21 -> 1587348 | DJ2: =DataForm!E21 -> 392394.24 | DK2: =DataForm!F21 -> 0 | DL2: =DataForm!G21 -> 0 | DM2: =DataForm!H21 -> 0 | DN2: =DataForm!I21 -> 0 | DO2: =DataForm!J21 -> 0 | DP2: =DataForm!K21 -> 0 | DQ2: =DataForm!N21 -> 0 | DR2: =DataForm!M21 -> 0 | DS2: =DataForm!O21 -> 9000 | DT2: =DataForm!P21 -> 0 | DU2: =DataForm!R21 -> 0.03 | DV2: =DataForm!S21 -> 0.08 | DW2: =DataForm!T21 -> 0.1 | DX2: =DataForm!V21 -> 0 | DY2: =DataForm!W21 -> 0 | DZ2: =DataForm!C22 -> 0 | EA2: =DataForm!D22 -> 0 | EB2: =DataForm!E22 -> 0 | EC2: =DataForm!F22 -> 0 | ED2: =DataForm!G22 -> 0 | EE2: =DataForm!H22 -> 0 | EF2: =DataForm!I22 -> 0 | EG2: =DataForm!J22 -> 0 | EH2: =DataForm!K22 -> 0 | EI2: =DataForm!N22 -> 0 | EJ2: =DataForm!M22 -> 0 | EK2: =DataForm!O22 -> 640092 | EL2: =DataForm!P22 -> 0 | EM2: =DataForm!R22 -> 0.03 | EN2: =DataForm!S22 -> 0.08 | EO2: =DataForm!T22 -> 0.1 | EP2: =DataForm!V22 -> 0 | EQ2: =DataForm!W22 -> 0 | ER2: =DataForm!C23 -> 0 | ES2: =DataForm!D23 -> 0 | ET2: =DataForm!E23 -> 0 | EU2: =DataForm!F23 -> 0 | EV2: =DataForm!G23 -> 0 | EW2: =DataForm!H23 -> 0 | EX2: =DataForm!I23 -> 0 | EY2: =DataForm!J23 -> 0 | EZ2: =DataForm!K23 -> 710850 | FA2: =DataForm!N23 -> 0 | FB2: =DataForm!M23 -> 0 | FC2: =DataForm!O23 -> 0 | FD2: =DataForm!P23 -> 278517 | FE2: =DataForm!R23 -> 0.03 | FF2: =DataForm!S23 -> 0.08 | FG2: =DataForm!T23 -> 0.1 | FH2: =DataForm!V23 -> 0 | FI2: =DataForm!W23 -> 0 | FJ2: =DataForm!C26 -> 7356327.5 | FK2: =DataForm!D26 -> 0 | FL2: =DataForm!E26 -> 5158218.3 | FM2: =DataForm!F26 -> 0 | FN2: =DataForm!G26 -> 124966.1 | FO2: =DataForm!H26 -> 0 | FP2: =DataForm!I26 -> 0 | FQ2: =DataForm!J26 -> 0 | FR2: =DataForm!K26 -> 1032569.4 | FS2: =DataForm!N26 -> 3167992.7 | FT2: =DataForm!M26 -> 1594757.4 | FU2: =DataForm!O26 -> 18119181 | FV2: =DataForm!P26 -> 0 | FW2: =DataForm!R26 -> 0 | FX2: =DataForm!S26 -> 0 | FY2: =DataForm!T26 -> 0 | FZ2: =DataForm!V26 -> 0 | GA2: =DataForm!W26 -> 0 | GB2: =DataForm!C27 -> 0 | GC2: =DataForm!D27 -> 4195698.5 | GD2: =DataForm!E27 -> 1784404.5 | GE2: =DataForm!F27 -> 1169229 | GF2: =DataForm!G27 -> 0 | GG2: =DataForm!H27 -> 0 | GH2: =DataForm!I27 -> 0 | GI2: =DataForm!J27 -> 0 | GJ2: =DataForm!K27 -> 3062771.8 | GK2: =DataForm!N27 -> 285192.73 | GL2: =DataForm!M27 -> 505625.88 | GM2: =DataForm!O27 -> 594879.56 | GN2: =DataForm!P27 -> 0 | GO2: =DataForm!R27 -> 0.03 | GP2: =DataForm!S27 -> 0.08 | GQ2: =DataForm!T27 -> 0.1 | GR2: =DataForm!V27 -> 0 | GS2: =DataForm!W27 -> 0 | GT2: =DataForm!C28 -> 0 | GU2: =DataForm!D28 -> 0 | GV2: =DataForm!E28 -> 0 | GW2: =DataForm!F28 -> 0 | GX2: =DataForm!G28 -> 0 | GY2: =DataForm!H28 -> 0 | GZ2: =DataForm!I28 -> 0 | HA2: =DataForm!J28 -> 0 | HB2: =DataForm!K28 -> 0 | HC2: =DataForm!N28 -> 0 | HD2: =DataForm!M28 -> 0 | HE2: =DataForm!O28 -> 0 | HF2: =DataForm!P28 -> 0 | HG2: =DataForm!R28 -> 0 | HH2: =DataForm!S28 -> 0 | HI2: =DataForm!T28 -> 0 | HJ2: =DataForm!V28 -> 0 | HK2: =DataForm!W28 -> 0 | HL2: =DataForm!C29 -> 0 | HM2: =DataForm!D29 -> 0 | HN2: =DataForm!E29 -> 0 | HO2: =DataForm!F29 -> 0 | HP2: =DataForm!G29 -> 0 | HQ2: =DataForm!H29 -> 0 | HR2: =DataForm!I29 -> 0 | HS2: =DataForm!J29 -> 0 | HT2: =DataForm!K29 -> 0 | HU2: =DataForm!N29 -> 0 | HV2: =DataForm!M29 -> 0 | HW2: =DataForm!O29 -> 0 | HX2: =DataForm!P29 -> 0 | HY2: =DataForm!R29 -> 0 | HZ2: =DataForm!S29 -> 0 | IA2: =DataForm!T29 -> 0 | IB2: =DataForm!V29 -> 0 | IC2: =DataForm!W29 -> 0 | ID2: =DataForm!C30 -> 0 | IE2: =DataForm!D30 -> 3689010.5 | IF2: =DataForm!E30 -> 1528666.9 | IG2: =DataForm!F30 -> 0 | IH2: =DataForm!G30 -> 0 | II2: =DataForm!H30 -> 0 | IJ2: =DataForm!I30 -> 11517888 | IK2: =DataForm!J30 -> 0 | IL2: =DataForm!K30 -> 745441.98 | IM2: =DataForm!N30 -> 0 | IN2: =DataForm!M30 -> 862906.82 | IO2: =DataForm!O30 -> 524164.75 | IP2: =DataForm!P30 -> 90340.93 | IQ2: =DataForm!R30 -> 0.03 | IR2: =DataForm!S30 -> 0.08 | IS2: =DataForm!T30 -> 0.1 | IT2: =DataForm!V30 -> 0 | IU2: =DataForm!W30 -> 0 | IV2: =DataForm!C31 -> 0 | IW2: =DataForm!D31 -> 0 | IX2: =DataForm!E31 -> 0 | IY2: =DataForm!F31 -> 0 | IZ2: =DataForm!G31 -> 0 | JA2: =DataForm!H31 -> 0 | JB2: =DataForm!I31 -> 0 | JC2: =DataForm!J31 -> 0 | JD2: =DataForm!K31 -> 0 | JE2: =DataForm!N31 -> 0 | JF2: =DataForm!M31 -> 0 | JG2: =DataForm!O31 -> 0 | JH2: =DataForm!P31 -> 0 | JI2: =DataForm!R31 -> 0 | JJ2: =DataForm!S31 -> 0 | JK2: =DataForm!T31 -> 0 | JL2: =DataForm!V31 -> 0 | JM2: =DataForm!W31 -> 0 | JN2: =DataForm!C32 -> 0 | JO2: =DataForm!D32 -> 539137.32 | JP2: =DataForm!E32 -> 182602.24 | JQ2: =DataForm!F32 -> 0 | JR2: =DataForm!G32 -> 0 | JS2: =DataForm!H32 -> 594704.98 | JT2: =DataForm!I32 -> 0 | JU2: =DataForm!J32 -> 2292676.3 | JV2: =DataForm!K32 -> 458210.95 | JW2: =DataForm!N32 -> 0 | JX2: =DataForm!M32 -> 861038.34 | JY2: =DataForm!O32 -> 0 | JZ2: =DataForm!P32 -> 12727.864 | KA2: =DataForm!R32 -> 0.03 | KB2: =DataForm!S32 -> 0.08 | KC2: =DataForm!T32 -> 0.1 | KD2: =DataForm!V32 -> 0 | KE2: =DataForm!W32 -> 0 | KF2: =DataForm!C33 -> 0 | KG2: =DataForm!D33 -> 1201058.1 | KH2: =DataForm!E33 -> 132857.89 | KI2: =DataForm!F33 -> 0 | KJ2: =DataForm!G33 -> 0 | KK2: =DataForm!H33 -> 0 | KL2: =DataForm!I33 -> 0 | KM2: =DataForm!J33 -> 0 | KN2: =DataForm!K33 -> 0 | KO2: =DataForm!N33 -> 0 | KP2: =DataForm!M33 -> 285211.68 | KQ2: =DataForm!O33 -> 0 | KR2: =DataForm!P33 -> 3840024.6 | KS2: =DataForm!R33 -> 0.03 | KT2: =DataForm!S33 -> 0.08 | KU2: =DataForm!T33 -> 0.1 | KV2: =DataForm!V33 -> 0 | KW2: =DataForm!W33 -> 0 | KX2: =DataForm!C34 -> 0 | KY2: =DataForm!D34 -> 0 | KZ2: =DataForm!E34 -> 0 | LA2: =DataForm!F34 -> 0 | LB2: =DataForm!G34 -> 0 | LC2: =DataForm!H34 -> 0 | LD2: =DataForm!I34 -> 0 | LE2: =DataForm!J34 -> 0 | LF2: =DataForm!K34 -> 0 | LG2: =DataForm!N34 -> 0 | LH2: =DataForm!M34 -> 0 | LI2: =DataForm!O34 -> 0 | LJ2: =DataForm!P34 -> 0 | LK2: =DataForm!R34 -> 0 | LL2: =DataForm!S34 -> 0 | LM2: =DataForm!T34 -> 0 | LN2: =DataForm!V34 -> 0 | LO2: =DataForm!W34 -> 0 | LP2: =DataForm!C37 -> 0 | LQ2: =DataForm!D37 -> 0 | LR2: =DataForm!E37 -> 0 | LS2: =DataForm!F37 -> 0 | LT2: =DataForm!G37 -> 0 | LU2: =DataForm!H37 -> 0 | LV2: =DataForm!I37 -> 0 | LW2: =DataForm!J37 -> 0 | LX2: =DataForm!K37 -> 0 | LY2: =DataForm!N37 -> 0 | LZ2: =DataForm!M37 -> 0 | MA2: =DataForm!O37 -> 0 | MB2: =DataForm!P37 -> 0 | MC2: =DataForm!R37 -> 0 | MD2: =DataForm!S37 -> 0 | ME2: =DataForm!T37 -> 0 | MF2: =DataForm!V37 -> 0 | MG2: =DataForm!W37 -> 0 | MH2: =DataForm!C38 -> 0 | MI2: =DataForm!D38 -> 18499.78 | MJ2: =DataForm!E38 -> 5592.7031 | MK2: =DataForm!F38 -> 0 | ML2: =DataForm!G38 -> 0 | MM2: =DataForm!H38 -> 0 | MN2: =DataForm!I38 -> 0 | MO2: =DataForm!J38 -> 0 | MP2: =DataForm!K38 -> 0 | MQ2: =DataForm!N38 -> 0 | MR2: =DataForm!M38 -> 68202.5 | MS2: =DataForm!O38 -> 0 | MT2: =DataForm!P38 -> 0 | MU2: =DataForm!R38 -> 0.03 | MV2: =DataForm!S38 -> 0.08 | MW2: =DataForm!T38 -> 0.1843 | MX2: =DataForm!V38 -> 0 | MY2: =DataForm!W38 -> 0 | MZ2: =DataForm!C40 -> 0 | NA2: =DataForm!D40 -> 0 | NB2: =DataForm!E40 -> 0 | NC2: =DataForm!F40 -> 0 | ND2: =DataForm!G40 -> 0 | NE2: =DataForm!H40 -> 0 | NF2: =DataForm!I40 -> 0 | NG2: =DataForm!J40 -> 0 | NH2: =DataForm!K40 -> 0 | NI2: =DataForm!N40 -> 0 | NJ2: =DataForm!M40 -> 0 | NK2: =DataForm!O40 -> 0 | NL2: =DataForm!P40 -> 0 | NM2: =DataForm!R40 -> 0 | NN2: =DataForm!S40 -> 0 | NO2: =DataForm!T40 -> 0 | NP2: =DataForm!V40 -> 0 | NQ2: =DataForm!W40 -> 0 | NR2: =Equipment_Total!C6 -> 2354062.2 | NS2: =Equipment_Total!C7 -> 0 | NT2: =Equipment_Total!C8 -> 0 | NU2: =Equipment_Total!C9 -> 0 | NV2: =Equipment_Total!C10 -> 0 | NW2: =Equipment_Total!C11 -> 275140.44 | NX2: =Equipment_Total!C12 -> 857500.99 | NY2: =Equipment_Total!C13 -> 310302.36 | NZ2: =Equipment_Total!C14 -> 0 | OA2: =Equipment_Total!C15 -> 0 | OB2: =Equipment_Total!C16 -> 0 | OC2: =Equipment_Total!C19 -> 2 | OD2: =Equipment_Total!C20 -> 0 | OE2: =Equipment_Total!C21 -> 2 | OF2: =Equipment_Total!C22 -> 3 | OG2: =Equipment_Total!C23 -> 1 | OH2: =Equipment_Total!C24 -> 0 | OI2: =Equipment_Total!C25 -> 0 | OJ2: =Equipment_Total!C26 -> 0 | OK2: =Equipment_Total!C27 -> 0 | OL2: =Equipment_Total!C28 -> 0 | OM2: =Equipment_Total!C29 -> 0 | ON2: =Equipment_Total!C33 -> 21914.4 | OO2: =Equipment_Total!C34 -> 0 | OP2: =Equipment_Total!C32 -> 0 | OQ2: =Equipment_Total!D6 -> 334492.85 | OR2: =Equipment_Total!D7 -> 0 | OS2: =Equipment_Total!D8 -> 0 | OT2: =Equipment_Total!D9 -> 0 | OU2: =Equipment_Total!D10 -> 0 | OV2: =Equipment_Total!D11 -> 62673.885 | OW2: =Equipment_Total!D12 -> 66521.187 | OX2: =Equipment_Total!D13 -> 117823.74 | OY2: =Equipment_Total!D14 -> 0 | OZ2: =Equipment_Total!D15 -> 0 | PA2: =Equipment_Total!D16 -> 0 | PB2: =Equipment_Total!D19 -> 0 | PC2: =Equipment_Total!D20 -> 0 | PD2: =Equipment_Total!D21 -> 0 | PE2: =Equipment_Total!D22 -> 0 | PF2: =Equipment_Total!D23 -> 0 | PG2: =Equipment_Total!D24 -> 0 | PH2: =Equipment_Total!D25 -> 0 | PI2: =Equipment_Total!D26 -> 0 | PJ2: =Equipment_Total!D27 -> 0 | PK2: =Equipment_Total!D28 -> 0 | PL2: =Equipment_Total!D29 -> 0 | PM2: =Equipment_Total!D33 -> 4557.6 | PN2: =Equipment_Total!D34 -> 0 | PO2: =Equipment_Total!D32 -> 0 | PP2: =Equipment_Total!E6 -> 2815545 | PQ2: =Equipment_Total!E7 -> 0 | PR2: =Equipment_Total!E8 -> 0 | PS2: =Equipment_Total!E9 -> 0 | PT2: =Equipment_Total!E10 -> 0 | PU2: =Equipment_Total!E11 -> 117267.18 | PV2: =Equipment_Total!E12 -> 282038.92 | PW2: =Equipment_Total!E13 -> 242148.61 | PX2: =Equipment_Total!E14 -> 0 | PY2: =Equipment_Total!E15 -> 0 | PZ2: =Equipment_Total!E16 -> 0 | QA2: =Equipment_Total!E19 -> 0 | QB2: =Equipment_Total!E20 -> 0 | QC2: =Equipment_Total!E21 -> 0 | QD2: =Equipment_Total!E22 -> 0 | QE2: =Equipment_Total!E23 -> 0 | QF2: =Equipment_Total!E24 -> 0 | QG2: =Equipment_Total!E25 -> 0 | QH2: =Equipment_Total!E26 -> 0 | QI2: =Equipment_Total!E27 -> 0 | QJ2: =Equipment_Total!E28 -> 0 | QK2: =Equipment_Total!E29 -> 0 | QL2: =Equipment_Total!E33 -> 11904 | QM2: =Equipment_Total!E34 -> 0 | QN2: =Equipment_Total!E32 -> 0 | QO2: =Equipment_Total!F6 -> 222026.51 | QP2: =Equipment_Total!F7 -> 0 | QQ2: =Equipment_Total!F8 -> 0 | QR2: =Equipment_Total!F9 -> 0 | QS2: =Equipment_Total!F10 -> 0 | QT2: =Equipment_Total!F11 -> 73772.659 | QU2: =Equipment_Total!F12 -> 211804.95 | QV2: =Equipment_Total!F13 -> 58538.895 | QW2: =Equipment_Total!F14 -> 0 | QX2: =Equipment_Total!F15 -> 0 | QY2: =Equipment_Total!F16 -> 0 | QZ2: =Equipment_Total!F19 -> 0 | RA2: =Equipment_Total!F20 -> 0 | RB2: =Equipment_Total!F21 -> 0 | RC2: =Equipment_Total!F22 -> 0 | RD2: =Equipment_Total!F23 -> 0 | RE2: =Equipment_Total!F24 -> 0 | RF2: =Equipment_Total!F25 -> 0 | RG2: =Equipment_Total!F26 -> 0 | RH2: =Equipment_Total!F27 -> 0 | RI2: =Equipment_Total!F28 -> 0 | RJ2: =Equipment_Total!F29 -> 0 | RK2: =Equipment_Total!F33 -> 4101.6 | RL2: =Equipment_Total!F34 -> 0 | RM2: =Equipment_Total!F32 -> 0 | RN2: =Equipment_Total!K6 -> 0 | RO2: =Equipment_Total!K7 -> 0 | RP2: =Equipment_Total!K8 -> 0 | RQ2: =Equipment_Total!K9 -> 0 | RR2: =Equipment_Total!K10 -> 0 | RS2: =Equipment_Total!K11 -> 0 | RT2: =Equipment_Total!K12 -> 723696.51 | RU2: =Equipment_Total!K13 -> 0 | RV2: =Equipment_Total!K14 -> 0 | RW2: =Equipment_Total!K15 -> 578957.2 | RX2: =Equipment_Total!K16 -> 0 | RY2: =Equipment_Total!K19 -> 1974148.8 | RZ2: =Equipment_Total!K20 -> 1164837.9 | SA2: =Equipment_Total!K21 -> 1286488.8 | SB2: =Equipment_Total!K22 -> 923931.75 | SC2: =Equipment_Total!K23 -> 1472276.3 | SD2: =Equipment_Total!K24 -> 168000 | SE2: =Equipment_Total!K25 -> 349782.4 | SF2: =Equipment_Total!K26 -> 1064315.1 | SG2: =Equipment_Total!K27 -> 99254.52 | SH2: =Equipment_Total!K28 -> 1257345 | SI2: =Equipment_Total!K29 -> 490043.88 | SJ2: =Equipment_Total!K33 -> 132122.88 | SK2: =Equipment_Total!K34 -> 334090.88 | SL2: =Equipment_Total!K32 -> 0 | SM2: =Equipment_Total!B6 -> 1 | SN2: =Equipment_Total!B7 -> 0 | SO2: =Equipment_Total!B8 -> 0 | SP2: =Equipment_Total!B9 -> 0 | SQ2: =Equipment_Total!B10 -> 0 | SR2: =Equipment_Total!B11 -> 1 | SS2: =Equipment_Total!B12 -> 3 | ST2: =Equipment_Total!B13 -> 3 | SU2: =Equipment_Total!B14 -> 0 | SV2: =Equipment_Total!B15 -> 2 | SW2: =Equipment_Total!B16 -> 0 | SX2: =Equipment_Total!B19 -> 7 | SY2: =Equipment_Total!B20 -> 2 | SZ2: =Equipment_Total!B21 -> 2 | TA2: =Equipment_Total!B22 -> 4 | TB2: =Equipment_Total!B23 -> 16 | TC2: =Equipment_Total!B24 -> 1 | TD2: =Equipment_Total!B25 -> 1 | TE2: =Equipment_Total!B26 -> 4 | TF2: =Equipment_Total!B27 -> 2 | TG2: =Equipment_Total!B28 -> 5 | TH2: =Equipment_Total!B29 -> 0 | TI2: =Equipment_Total!B33 -> 0 | TJ2: =Equipment_Total!B34 -> 0 | TK2: =Equipment_Total!B32 -> 0 | TL2: =Equipment_Total!H6 -> 915819.01 | TM2: =Equipment_Total!H7 -> 0 | TN2: =Equipment_Total!H8 -> 0 | TO2: =Equipment_Total!H9 -> 0 | TP2: =Equipment_Total!H10 -> 0 | TQ2: =Equipment_Total!H11 -> 43968.074 | TR2: =Equipment_Total!H12 -> 137213.88 | TS2: =Equipment_Total!H13 -> 53512.435 | TT2: =Equipment_Total!H14 -> 0 | TU2: =Equipment_Total!H15 -> 0 | TV2: =Equipment_Total!H16 -> 0 | TW2: =Equipment_Total!H19 -> 0 | TX2: =Equipment_Total!H20 -> 0 | TY2: =Equipment_Total!H21 -> 0 | TZ2: =Equipment_Total!H22 -> 0 | UA2: =Equipment_Total!H23 -> 0 | UB2: =Equipment_Total!H24 -> 0 | UC2: =Equipment_Total!H25 -> 0 | UD2: =Equipment_Total!H26 -> 0 | UE2: =Equipment_Total!H27 -> 0 | UF2: =Equipment_Total!H28 -> 0 | UG2: =Equipment_Total!H29 -> 0 | UH2: =Equipment_Total!H33 -> 3232.8 | UI2: =Equipment_Total!H34 -> 0 | UJ2: =Equipment_Total!H32 -> 0 | UK2: =Equipment_Total!I6 -> 905358.57 | UL2: =Equipment_Total!I7 -> 0 | UM2: =Equipment_Total!I8 -> 0 | UN2: =Equipment_Total!I9 -> 0 | UO2: =Equipment_Total!I10 -> 0 | UP2: =Equipment_Total!I11 -> 251280.35 | UQ2: =Equipment_Total!I12 -> 373312.93 | UR2: =Equipment_Total!I13 -> 380793.93 | US2: =Equipment_Total!I14 -> 0 | UT2: =Equipment_Total!I15 -> 0 | UU2: =Equipment_Total!I16 -> 0 | UV2: =Equipment_Total!I19 -> 0 | UW2: =Equipment_Total!I20 -> 0 | UX2: =Equipment_Total!I21 -> 0 | UY2: =Equipment_Total!I22 -> 0 | UZ2: =Equipment_Total!I23 -> 0 | VA2: =Equipment_Total!I24 -> 0 | VB2: =Equipment_Total!I25 -> 0 | VC2: =Equipment_Total!I26 -> 0 | VD2: =Equipment_Total!I27 -> 0 | VE2: =Equipment_Total!I28 -> 0 | VF2: =Equipment_Total!I29 -> 0 | VG2: =Equipment_Total!I33 -> 17635.2 | VH2: =Equipment_Total!I34 -> 0 | VI2: =Equipment_Total!I32 -> 0 | VJ2: =Equipment_Total!J6 -> 1990806.9 | VK2: =Equipment_Total!J7 -> 0 | VL2: =Equipment_Total!J8 -> 0 | VM2: =Equipment_Total!J9 -> 0 | VN2: =Equipment_Total!J10 -> 0 | VO2: =Equipment_Total!J11 -> 151607.88 | VP2: =Equipment_Total!J12 -> 975938.06 | VQ2: =Equipment_Total!J13 -> 146113.31 | VR2: =Equipment_Total!J14 -> 0 | VS2: =Equipment_Total!J15 -> 0 | VT2: =Equipment_Total!J16 -> 0 | VU2: =Equipment_Total!J19 -> 0 | VV2: =Equipment_Total!J20 -> 0 | VW2: =Equipment_Total!J21 -> 0 | VX2: =Equipment_Total!J22 -> 0 | VY2: =Equipment_Total!J23 -> 0 | VZ2: =Equipment_Total!J24 -> 0 | WA2: =Equipment_Total!J25 -> 0 | WB2: =Equipment_Total!J26 -> 0 | WC2: =Equipment_Total!J27 -> 0 | WD2: =Equipment_Total!J28 -> 0 | WE2: =Equipment_Total!J29 -> 0 | WF2: =Equipment_Total!J33 -> 48507.6 | WG2: =Equipment_Total!J34 -> 0 | WH2: =Equipment_Total!J32 -> 0
